{
    "m000000501966.jpg": {
        "subject": "30",
        "dataset": "MCS Dataset",
        "image_height": 508,
        "image_width": 564,
        "screen_height": 800,
        "screen_width": 1280,
        "receptive_height": 10,
        "receptive_width": 10,
        "target_found": true,
        "target_bbox": [
            323,
            361,
            499,
            562
        ],
        "X": [
            285.96978540772534,
            260.2145922746781,
            350.2609442060086,
            420.3615450643777,
            524.7862660944206
        ],
        "Y": [
            252.46866952789702,
            210.25339055793992,
            295.7006008583691,
            290.13321888412014,
            332.39690987124465
        ],
        "T": [
            100,
            154,
            246,
            210,
            227
        ],
        "target_object": "microwave",
        "max_fixations": 80
    },
    "m000000581118.jpg": {
        "subject": "30",
        "dataset": "MCS Dataset",
        "image_height": 508,
        "image_width": 564,
        "screen_height": 800,
        "screen_width": 1280,
        "receptive_height": 10,
        "receptive_width": 10,
        "target_found": true,
        "target_bbox": [
            344,
            200,
            505,
            516
        ],
        "X": [
            283.258712446352,
            218.48343347639485,
            355.4410300429185
        ],
        "Y": [
            256.147982832618,
            106.40961373390559,
            360.96000000000004
        ],
        "T": [
            281,
            200,
            204
        ],
        "target_object": "microwave",
        "max_fixations": 80
    },
    "m000000324365.jpg": {
        "subject": "30",
        "dataset": "MCS Dataset",
        "image_height": 508,
        "image_width": 564,
        "screen_height": 800,
        "screen_width": 1280,
        "receptive_height": 10,
        "receptive_width": 10,
        "target_found": false,
        "target_bbox": [
            115,
            0,
            140,
            27
        ],
        "X": [
            297.10454935622323,
            459.4784549356223,
            206.5256652360515,
            20.333047210300432,
            42.79622317596566,
            1.7912446351931277,
            57.94918454935622,
            -49.47708154506437,
            60.12772532188841,
            67.58317596566525,
            41.9248068669528,
            -0.1936480686695169,
            -46.37871244635194,
            -47.056480686695274,
            -35.582832618025755,
            -46.28188841201717
        ],
        "Y": [
            256.5836909871245,
            236.88000000000002,
            192.77665236051502,
            203.66935622317598,
            170.70077253218886,
            165.13339055793995,
            168.1349356223176,
            175.5903862660944,
            172.83090128755364,
            169.53888412017167,
            170.60394849785408,
            168.61905579399144,
            171.3301287553648,
            133.32669527896996,
            139.03931330472102,
            138.45836909871247
        ],
        "T": [
            221,
            268,
            230,
            248,
            160,
            209,
            234,
            337,
            284,
            178,
            200,
            434,
            219,
            322,
            232,
            164
        ],
        "target_object": "microwave",
        "max_fixations": 80
    },
    "m000000270179.jpg": {
        "subject": "30",
        "dataset": "MCS Dataset",
        "image_height": 508,
        "image_width": 564,
        "screen_height": 800,
        "screen_width": 1280,
        "receptive_height": 10,
        "receptive_width": 10,
        "target_found": true,
        "target_bbox": [
            143,
            235,
            236,
            363
        ],
        "X": [
            288.09991416309015,
            332.59055793991416
        ],
        "Y": [
            257.6971673819742,
            171.76583690987127
        ],
        "T": [
            224,
            276
        ],
        "target_object": "microwave",
        "max_fixations": 80
    },
    "m000000198108.jpg": {
        "subject": "30",
        "dataset": "MCS Dataset",
        "image_height": 508,
        "image_width": 564,
        "screen_height": 800,
        "screen_width": 1280,
        "receptive_height": 10,
        "receptive_width": 10,
        "target_found": true,
        "target_bbox": [
            188,
            455,
            220,
            509
        ],
        "X": [
            283.1134763948498,
            214.70729613733906,
            160.43742489270386,
            395.3809442060086,
            435.07879828326185,
            446.26197424892706,
            418.2798283261803,
            431.5931330472103,
            410.001373390558,
            413.3418025751073,
            329.9278969957082,
            249.70918454935622,
            197.42420600858367,
            137.19965665236052,
            127.46884120171673,
            426.2678111587983,
            436.3375107296137,
            405.2569957081545,
            446.891330472103
        ],
        "Y": [
            256.390042918455,
            234.26575107296136,
            233.68480686695278,
            196.50437768240343,
            216.83742489270386,
            272.4144206008584,
            215.62712446351932,
            211.1248068669528,
            195.34248927038627,
            177.67210300429184,
            206.96137339055795,
            206.38042918454937,
            214.22317596566523,
            251.83931330472106,
            220.8072103004292,
            200.03845493562233,
            203.76618025751074,
            198.73133047210302,
            210.25339055793992
        ],
        "T": [
            319,
            173,
            144,
            205,
            371,
            190,
            324,
            270,
            211,
            194,
            142,
            450,
            314,
            236,
            323,
            336,
            82,
            303,
            205
        ],
        "target_object": "microwave",
        "max_fixations": 80
    },
    "m000000396097.jpg": {
        "subject": "30",
        "dataset": "MCS Dataset",
        "image_height": 508,
        "image_width": 564,
        "screen_height": 800,
        "screen_width": 1280,
        "receptive_height": 10,
        "receptive_width": 10,
        "target_found": false,
        "target_bbox": [
            282,
            337,
            317,
            373
        ],
        "X": [
            287.27690987124464,
            281.4674678111588,
            482.5709871244635,
            510.69836909871253,
            388.31278969957077,
            414.01957081545066,
            424.7186266094421
        ],
        "Y": [
            259.1979399141631,
            235.86334763948497,
            271.34935622317596,
            205.5574248927039,
            298.4600858369099,
            298.21802575107296,
            302.42987124463525
        ],
        "T": [
            57,
            156,
            94,
            148,
            185,
            245,
            230
        ],
        "target_object": "microwave",
        "max_fixations": 80
    },
    "m000000488894.jpg": {
        "subject": "30",
        "dataset": "MCS Dataset",
        "image_height": 508,
        "image_width": 564,
        "screen_height": 800,
        "screen_width": 1280,
        "receptive_height": 10,
        "receptive_width": 10,
        "target_found": true,
        "target_bbox": [
            293,
            379,
            363,
            468
        ],
        "X": [
            286.7443776824034,
            475.55124463519314
        ],
        "Y": [
            254.40515021459228,
            286.8896137339056
        ],
        "T": [
            245,
            189
        ],
        "target_object": "microwave",
        "max_fixations": 80
    },
    "m000000274213.jpg": {
        "subject": "30",
        "dataset": "MCS Dataset",
        "image_height": 508,
        "image_width": 564,
        "screen_height": 800,
        "screen_width": 1280,
        "receptive_height": 10,
        "receptive_width": 10,
        "target_found": false,
        "target_bbox": [
            261,
            51,
            324,
            105
        ],
        "X": [
            284.1785407725322,
            318.40583690987125,
            159.3239484978541,
            55.57699570815451,
            33.21064377682405,
            14.95931330472102
        ],
        "Y": [
            252.08137339055799,
            227.19759656652363,
            189.4362231759657,
            228.3594849785408,
            290.71416309012875,
            282.29047210300433
        ],
        "T": [
            73,
            43,
            130,
            218,
            218,
            321
        ],
        "target_object": "microwave",
        "max_fixations": 80
    },
    "m000000332463.jpg": {
        "subject": "30",
        "dataset": "MCS Dataset",
        "image_height": 508,
        "image_width": 564,
        "screen_height": 800,
        "screen_width": 1280,
        "receptive_height": 10,
        "receptive_width": 10,
        "target_found": true,
        "target_bbox": [
            203,
            309,
            238,
            358
        ],
        "X": [
            293.23158798283265,
            295.60377682403436,
            489.2034334763949,
            381.58351931330475,
            368.5122746781116,
            340.046008583691
        ],
        "Y": [
            257.0678111587983,
            233.9268669527897,
            205.07330472103007,
            224.68017167381976,
            227.19759656652363,
            228.3110729613734
        ],
        "T": [
            96,
            188,
            129,
            319,
            490,
            339
        ],
        "target_object": "microwave",
        "max_fixations": 80
    },
    "m000000382615.jpg": {
        "subject": "30",
        "dataset": "MCS Dataset",
        "image_height": 508,
        "image_width": 564,
        "screen_height": 800,
        "screen_width": 1280,
        "receptive_height": 10,
        "receptive_width": 10,
        "target_found": true,
        "target_bbox": [
            170,
            361,
            379,
            455
        ],
        "X": [
            280.11193133047215,
            448.6341630901288
        ],
        "Y": [
            260.2630042918455,
            260.6987124463519
        ],
        "T": [
            321,
            236
        ],
        "target_object": "microwave",
        "max_fixations": 80
    },
    "m000000112882.jpg": {
        "subject": "30",
        "dataset": "MCS Dataset",
        "image_height": 508,
        "image_width": 564,
        "screen_height": 800,
        "screen_width": 1280,
        "receptive_height": 10,
        "receptive_width": 10,
        "target_found": true,
        "target_bbox": [
            156,
            369,
            229,
            435
        ],
        "X": [
            293.0379399141631,
            443.212017167382,
            446.3103862660945,
            429.22094420600854
        ],
        "Y": [
            262.78042918454935,
            246.0782832618026,
            191.42111587982833,
            201.92652360515024
        ],
        "T": [
            240,
            196,
            345,
            197
        ],
        "target_object": "microwave",
        "max_fixations": 80
    },
    "m000000002448.jpg": {
        "subject": "30",
        "dataset": "MCS Dataset",
        "image_height": 508,
        "image_width": 564,
        "screen_height": 800,
        "screen_width": 1280,
        "receptive_height": 10,
        "receptive_width": 10,
        "target_found": false,
        "target_bbox": [
            179,
            335,
            215,
            355
        ],
        "X": [
            331.52549356223176,
            278.5627467811159,
            89.90111587982832,
            274.39931330472103,
            389.0389699570815,
            371.07811158798285
        ],
        "Y": [
            237.7514163090129,
            260.069356223176,
            236.15381974248928,
            192.0504721030043,
            208.07484978540774,
            205.9931330472103
        ],
        "T": [
            224,
            137,
            200,
            281,
            204,
            364
        ],
        "target_object": "microwave",
        "max_fixations": 80
    },
    "m000000470068.jpg": {
        "subject": "30",
        "dataset": "MCS Dataset",
        "image_height": 508,
        "image_width": 564,
        "screen_height": 800,
        "screen_width": 1280,
        "receptive_height": 10,
        "receptive_width": 10,
        "target_found": true,
        "target_bbox": [
            161,
            0,
            354,
            232
        ],
        "X": [
            283.5007725321889,
            147.07570815450643
        ],
        "Y": [
            256.92257510729615,
            217.3215450643777
        ],
        "T": [
            204,
            248
        ],
        "target_object": "microwave",
        "max_fixations": 80
    },
    "m000000058102.jpg": {
        "subject": "30",
        "dataset": "MCS Dataset",
        "image_height": 508,
        "image_width": 564,
        "screen_height": 800,
        "screen_width": 1280,
        "receptive_height": 10,
        "receptive_width": 10,
        "target_found": true,
        "target_bbox": [
            159,
            206,
            201,
            270
        ],
        "X": [
            286.0666094420601,
            223.56669527896995
        ],
        "Y": [
            254.9376824034335,
            176.84909871244636
        ],
        "T": [
            221,
            385
        ],
        "target_object": "microwave",
        "max_fixations": 80
    },
    "m000000253992.jpg": {
        "subject": "30",
        "dataset": "MCS Dataset",
        "image_height": 508,
        "image_width": 564,
        "screen_height": 800,
        "screen_width": 1280,
        "receptive_height": 10,
        "receptive_width": 10,
        "target_found": false,
        "target_bbox": [
            184,
            400,
            262,
            479
        ],
        "X": [
            279.8214592274678,
            182.41648068669525,
            494.1898712446352,
            492.97957081545064
        ],
        "Y": [
            245.30369098712447,
            250.5806008583691,
            211.9478111587983,
            224.97064377682403
        ],
        "T": [
            266,
            97,
            300,
            89
        ],
        "target_object": "microwave",
        "max_fixations": 80
    },
    "m000000520975.jpg": {
        "subject": "30",
        "dataset": "MCS Dataset",
        "image_height": 508,
        "image_width": 564,
        "screen_height": 800,
        "screen_width": 1280,
        "receptive_height": 10,
        "receptive_width": 10,
        "target_found": true,
        "target_bbox": [
            220,
            433,
            407,
            564
        ],
        "X": [
            286.4054935622318,
            225.1158798283262,
            553.2041201716738
        ],
        "Y": [
            252.66231759656654,
            173.8475536480687,
            275.3191416309013
        ],
        "T": [
            247,
            78,
            191
        ],
        "target_object": "microwave",
        "max_fixations": 80
    },
    "m000000135822.jpg": {
        "subject": "30",
        "dataset": "MCS Dataset",
        "image_height": 508,
        "image_width": 564,
        "screen_height": 800,
        "screen_width": 1280,
        "receptive_height": 10,
        "receptive_width": 10,
        "target_found": true,
        "target_bbox": [
            221,
            220,
            245,
            253
        ],
        "X": [
            283.258712446352,
            235.233991416309,
            384.2461802575108,
            157.0969957081545,
            240.6077253218884,
            145.3328755364807,
            56.44841201716739,
            72.47278969957081,
            1.5975965665236107,
            192.14729613733905,
            352.7299570815451,
            244.480686695279
        ],
        "Y": [
            252.03296137339058,
            180.4315879828326,
            243.99656652360517,
            276.91673819742493,
            182.31965665236052,
            145.33287553648069,
            133.18145922746783,
            263.36137339055796,
            283.06506437768246,
            281.4674678111588,
            253.00120171673822,
            244.7711587982833
        ],
        "T": [
            219,
            244,
            249,
            285,
            256,
            155,
            251,
            243,
            124,
            197,
            177,
            350
        ],
        "target_object": "microwave",
        "max_fixations": 80
    },
    "m000000406298.jpg": {
        "subject": "30",
        "dataset": "MCS Dataset",
        "image_height": 508,
        "image_width": 564,
        "screen_height": 800,
        "screen_width": 1280,
        "receptive_height": 10,
        "receptive_width": 10,
        "target_found": true,
        "target_bbox": [
            122,
            484,
            252,
            515
        ],
        "X": [
            286.8896137339056,
            81.47742489270387,
            533.2583690987125,
            624.4666094420602,
            478.698025751073
        ],
        "Y": [
            254.9860944206009,
            285.53407725321887,
            288.8260944206009,
            302.91399141630905,
            226.27776824034333
        ],
        "T": [
            319,
            381,
            238,
            214,
            225
        ],
        "target_object": "microwave",
        "max_fixations": 80
    },
    "m000000297639.jpg": {
        "subject": "30",
        "dataset": "MCS Dataset",
        "image_height": 508,
        "image_width": 564,
        "screen_height": 800,
        "screen_width": 1280,
        "receptive_height": 10,
        "receptive_width": 10,
        "target_found": true,
        "target_bbox": [
            116,
            415,
            165,
            489
        ],
        "X": [
            279.3857510729614,
            275.17390557939916,
            463.2545922746782,
            510.16583690987125,
            530.0147639484978,
            474.2925321888412
        ],
        "Y": [
            252.66231759656654,
            223.27622317596567,
            203.66935622317598,
            147.80188841201718,
            145.23605150214593,
            145.67175965665237
        ],
        "T": [
            53,
            203,
            236,
            246,
            171,
            63
        ],
        "target_object": "microwave",
        "max_fixations": 80
    },
    "m000000309060.jpg": {
        "subject": "30",
        "dataset": "MCS Dataset",
        "image_height": 508,
        "image_width": 564,
        "screen_height": 800,
        "screen_width": 1280,
        "receptive_height": 10,
        "receptive_width": 10,
        "target_found": true,
        "target_bbox": [
            249,
            0,
            376,
            51
        ],
        "X": [
            286.4539055793992,
            349.34111587982835,
            556.3993133047211,
            119.09356223175966,
            51.02626609442059,
            -3.4372532188841176
        ],
        "Y": [
            250.48377682403432,
            220.8072103004292,
            216.45012875536483,
            244.6743347639485,
            226.47141630901288,
            290.66575107296137
        ],
        "T": [
            21,
            158,
            210,
            186,
            163,
            597
        ],
        "target_object": "microwave",
        "max_fixations": 80
    },
    "m000000177289.jpg": {
        "subject": "30",
        "dataset": "MCS Dataset",
        "image_height": 508,
        "image_width": 564,
        "screen_height": 800,
        "screen_width": 1280,
        "receptive_height": 10,
        "receptive_width": 10,
        "target_found": true,
        "target_bbox": [
            135,
            152,
            169,
            192
        ],
        "X": [
            277.78815450643776,
            494.28669527897,
            472.45287553648075,
            128.72755364806866,
            159.37236051502148
        ],
        "Y": [
            252.2750214592275,
            302.67193133047215,
            195.53613733905578,
            204.00824034334764,
            157.04858369098713
        ],
        "T": [
            231,
            164,
            156,
            230,
            233
        ],
        "target_object": "microwave",
        "max_fixations": 80
    },
    "m000000071726.jpg": {
        "subject": "30",
        "dataset": "MCS Dataset",
        "image_height": 508,
        "image_width": 564,
        "screen_height": 800,
        "screen_width": 1280,
        "receptive_height": 10,
        "receptive_width": 10,
        "target_found": true,
        "target_bbox": [
            241,
            440,
            306,
            519
        ],
        "X": [
            280.54763948497856,
            284.66266094420604,
            507.6
        ],
        "Y": [
            254.5987982832618,
            216.93424892703865,
            259.6336480686695
        ],
        "T": [
            47,
            217,
            345
        ],
        "target_object": "microwave",
        "max_fixations": 80
    },
    "m000000381661.jpg": {
        "subject": "30",
        "dataset": "MCS Dataset",
        "image_height": 508,
        "image_width": 564,
        "screen_height": 800,
        "screen_width": 1280,
        "receptive_height": 10,
        "receptive_width": 10,
        "target_found": true,
        "target_bbox": [
            256,
            135,
            315,
            189
        ],
        "X": [
            283.79124463519315,
            252.90437768240344,
            523.818025751073,
            389.76515021459227,
            549.2827467811159,
            261.5701287553648,
            276.5294420600859,
            149.4478969957082
        ],
        "Y": [
            255.85751072961375,
            208.60738197424894,
            254.79244635193132,
            275.2707296137339,
            280.6444635193133,
            305.09253218884123,
            272.6564806866953,
            287.80944206008587
        ],
        "T": [
            355,
            139,
            240,
            114,
            487,
            213,
            149,
            284
        ],
        "target_object": "microwave",
        "max_fixations": 80
    },
    "m000000474031.jpg": {
        "subject": "30",
        "dataset": "MCS Dataset",
        "image_height": 508,
        "image_width": 564,
        "screen_height": 800,
        "screen_width": 1280,
        "receptive_height": 10,
        "receptive_width": 10,
        "target_found": true,
        "target_bbox": [
            212,
            139,
            258,
            185
        ],
        "X": [
            284.1785407725322,
            187.49974248927037
        ],
        "Y": [
            220.17785407725324,
            233.3943347639485
        ],
        "T": [
            211,
            163
        ],
        "target_object": "microwave",
        "max_fixations": 80
    },
    "m000000077260.jpg": {
        "subject": "30",
        "dataset": "MCS Dataset",
        "image_height": 508,
        "image_width": 564,
        "screen_height": 800,
        "screen_width": 1280,
        "receptive_height": 10,
        "receptive_width": 10,
        "target_found": true,
        "target_bbox": [
            373,
            436,
            493,
            563
        ],
        "X": [
            276.4326180257511,
            286.938025751073,
            541.44,
            573.1014592274678,
            562.4508154506437
        ],
        "Y": [
            250.3869527896996,
            168.7158798283262,
            232.03879828326183,
            148.23759656652362,
            383.32635193133046
        ],
        "T": [
            218,
            120,
            223,
            217,
            213
        ],
        "target_object": "microwave",
        "max_fixations": 80
    }
}