{"grayscale_11_opensource.jpg": {"subject": "31", "dataset": "Interiors Dataset", "image_height": 768, "image_width": 1024, "screen_height": 960, "screen_width": 1280, "receptive_height": 32, "receptive_width": 32, "target_found": true, "target_bbox": [559, 228, 631, 300], "X": [642.2, 459.0, 380.6, 393.6, 692.0, 630.4, 442.0, 460.70000000000005, 368.3, 301.7, 196.0], "Y": [741.0, 382.1, 326.1, 193.5, 383.0, 395.4, 580.7, 600.0, 600.0, 594.5, 555.0], "T": [444, 178, 222, 317, 374, 260, 293, 155, 505, 500], "target_object": "TBD", "max_fixations": 13, "subject_name": "JCG", "initial_fixation_row": 754, "initial_fixation_column": 585, "response_x": 196.0, "response_y": 555.0, "response_size": 19, "response_click": 18.5332553324988, "response_circle": 42.2833092879155}, "grayscale_18_housebeautiful.jpg": {"subject": "31", "dataset": "Interiors Dataset", "image_height": 768, "image_width": 1024, "screen_height": 960, "screen_width": 1280, "receptive_height": 32, "receptive_width": 32, "target_found": false, "target_bbox": [400, 797, 472, 869], "X": [652.1, 700.0, 925.2, 815.8, 937.6, 1016.25, 461.4, 869.0], "Y": [407.5, 684.1, 767.0, 751.1, 559.9, 553.95, 617.5, 387.0], "T": [488, 186, 233, 137, 170, 278, 264, 251], "target_object": "potted plant", "max_fixations": 9, "subject_name": "JCG", "initial_fixation_row": 301, "initial_fixation_column": 501, "response_x": 869.0, "response_y": 387.0, "response_size": 19, "response_click": 3.28340693563223, "response_circle": 7.25021318270592}, "grayscale_100_oliva.jpg": {"subject": "31", "dataset": "Interiors Dataset", "image_height": 768, "image_width": 1024, "screen_height": 960, "screen_width": 1280, "receptive_height": 32, "receptive_width": 32, "target_found": true, "target_bbox": [381, 713, 453, 785], "X": [450.4, 564.3, 766.5, 770.0], "Y": [334.5, 360.2, 433.29999999999995, 440.0], "T": [339, 116, 524], "target_object": "potted plant", "max_fixations": 5, "subject_name": "JCG", "initial_fixation_row": 339, "initial_fixation_column": 400, "response_x": 770.0, "response_y": 440.0, "response_size": 11, "response_click": 2.48340957477922, "response_circle": 32.4834869891056}, "grayscale_17_oliva.jpg": {"subject": "31", "dataset": "Interiors Dataset", "image_height": 768, "image_width": 1024, "screen_height": 960, "screen_width": 1280, "receptive_height": 32, "receptive_width": 32, "target_found": false, "target_bbox": [490, 186, 562, 258], "X": [660.8, 358.7, 244.8, 223.0], "Y": [436.70000000000005, 481.1, 465.0, 521.0], "T": [1567, 228, 165], "target_object": "TBD", "max_fixations": 3, "subject_name": "JCG", "initial_fixation_row": 169, "initial_fixation_column": 245, "response_x": 223.0, "response_y": 521.0, "response_size": 13, "response_click": 2.75028707826277, "response_circle": 4.31711795722367}, "grayscale_16_housebeautiful.jpg": {"subject": "31", "dataset": "Interiors Dataset", "image_height": 768, "image_width": 1024, "screen_height": 960, "screen_width": 1280, "receptive_height": 32, "receptive_width": 32, "target_found": false, "target_bbox": [421, 158, 493, 230], "X": [676.0, 790.1, 889.9, 574.0], "Y": [488.8, 565.0, 566.1, 77.0], "T": [817, 181, 106, 393], "target_object": "TBD", "max_fixations": 3, "subject_name": "JCG", "initial_fixation_row": 119, "initial_fixation_column": 75, "response_x": 574.0, "response_y": 77.0, "response_size": 29, "response_click": 3.20016245282022, "response_circle": 7.33359959180234}, "grayscale_13_oliva.jpg": {"subject": "31", "dataset": "Interiors Dataset", "image_height": 768, "image_width": 1024, "screen_height": 960, "screen_width": 1280, "receptive_height": 32, "receptive_width": 32, "target_found": true, "target_bbox": [138, 785, 210, 857], "X": [650.3, 637.9, 770.1, 791.0], "Y": [329.3, 299.0, 207.3, 163.0], "T": [412, 351, 229, 147], "target_object": "TBD", "max_fixations": 5, "subject_name": "JCG", "initial_fixation_row": 293, "initial_fixation_column": 483, "response_x": 791.0, "response_y": 163.0, "response_size": 15, "response_click": 2.31669804290868, "response_circle": 4.08359548647422}, "grayscale_21_housebeautiful.jpg": {"subject": "31", "dataset": "Interiors Dataset", "image_height": 768, "image_width": 1024, "screen_height": 960, "screen_width": 1280, "receptive_height": 32, "receptive_width": 32, "target_found": false, "target_bbox": [373, 63, 445, 135], "X": [623.2, 706.6, 795.1, 556.2, 1023.0, 198.8, 159.0, 101.0], "Y": [482.7, 657.5, 736.4, 694.2, 456.6, 446.2, 435.1, 395.0], "T": [276, 166, 210, 75, 273, 145, 93], "target_object": "TBD", "max_fixations": 9, "subject_name": "JCG", "initial_fixation_row": 383, "initial_fixation_column": 456, "response_x": 101.0, "response_y": 395.0, "response_size": 15, "response_click": 1.95014221954625, "response_circle": 3.71699655737029}, "grayscale_72_oliva.jpg": {"subject": "31", "dataset": "Interiors Dataset", "image_height": 768, "image_width": 1024, "screen_height": 960, "screen_width": 1280, "receptive_height": 32, "receptive_width": 32, "target_found": false, "target_bbox": [328, 569, 400, 641], "X": [685.0, 558.4, 875.7, 1014.2, 1023.0, 1023.0, 508.9, 264.2, 670.4, 600.0], "Y": [454.1, 425.9, 415.79999999999995, 447.5, 475.79999999999995, 506.0, 575.0, 376.6, 295.2, 355.0], "T": [350, 178, 282, 73, 167, 263, 266, 195, 209], "target_object": "TBD", "max_fixations": 13, "subject_name": "JCG", "initial_fixation_row": 66, "initial_fixation_column": 407, "response_x": 600.0, "response_y": 355.0, "response_size": 15, "response_click": 1.95015629491536, "response_circle": 3.31690829334548}, "grayscale_21_kitchen.jpg": {"subject": "31", "dataset": "Interiors Dataset", "image_height": 768, "image_width": 1024, "screen_height": 960, "screen_width": 1280, "receptive_height": 32, "receptive_width": 32, "target_found": true, "target_bbox": [341, 747, 413, 819], "X": [610.0, 724.9, 825.7, 787.0], "Y": [277.1, 330.5, 359.0, 381.0], "T": [520, 143, 639], "target_object": "TBD", "max_fixations": 13, "subject_name": "JCG", "initial_fixation_row": 100, "initial_fixation_column": 1010, "response_x": 787.0, "response_y": 381.0, "response_size": 17, "response_click": 1.6168575634365, "response_circle": 3.05016362579772}, "grayscale_14_housebeautiful.jpg": {"subject": "31", "dataset": "Interiors Dataset", "image_height": 768, "image_width": 1024, "screen_height": 960, "screen_width": 1280, "receptive_height": 32, "receptive_width": 32, "target_found": true, "target_bbox": [578, 50, 650, 122], "X": [551.9, 604.8, 909.4, 78.1, 98.0], "Y": [373.8, 498.4, 547.8, 582.5, 607.0], "T": [213, 132, 268, 245], "target_object": "cup", "max_fixations": 13, "subject_name": "JCG", "initial_fixation_row": 751, "initial_fixation_column": 417, "response_x": 98.0, "response_y": 607.0, "response_size": 19, "response_click": 1.98359167441959, "response_circle": 3.48362568981247}, "grayscale_1_opensource.jpg": {"subject": "31", "dataset": "Interiors Dataset", "image_height": 768, "image_width": 1024, "screen_height": 960, "screen_width": 1280, "receptive_height": 32, "receptive_width": 32, "target_found": true, "target_bbox": [376, 700, 448, 772], "X": [559.9, 474.0, 766.9, 853.0], "Y": [347.3, 384.20000000000005, 387.9, 385.0], "T": [182, 52, 165], "target_object": "TBD", "max_fixations": 9, "subject_name": "JCG", "initial_fixation_row": 657, "initial_fixation_column": 997, "response_x": 853.0, "response_y": 385.0, "response_size": 27, "response_click": 1.4834720340441, "response_circle": 2.85027505556354}, "grayscale_11_oliva.jpg": {"subject": "31", "dataset": "Interiors Dataset", "image_height": 768, "image_width": 1024, "screen_height": 960, "screen_width": 1280, "receptive_height": 32, "receptive_width": 32, "target_found": true, "target_bbox": [216, 686, 288, 758], "X": [762.0, 496.0, 614.2, 766.1, 726.0], "Y": [329.8, 290.1, 190.8, 205.39999999999998, 258.0], "T": [275, 41, 97, 144], "target_object": "TBD", "max_fixations": 13, "subject_name": "JCG", "initial_fixation_row": 590, "initial_fixation_column": 840, "response_x": 726.0, "response_y": 258.0, "response_size": 17, "response_click": 1.55026215314865, "response_circle": 2.81695051933639}, "grayscale_30_housebeautiful.jpg": {"subject": "31", "dataset": "Interiors Dataset", "image_height": 768, "image_width": 1024, "screen_height": 960, "screen_width": 1280, "receptive_height": 32, "receptive_width": 32, "target_found": false, "target_bbox": [260, 680, 332, 752], "X": [510.3, 637.7, 630.4, 551.0], "Y": [530.7, 455.9, 339.4, 156.0], "T": [241, 156, 733], "target_object": "TBD", "max_fixations": 5, "subject_name": "JCG", "initial_fixation_row": 421, "initial_fixation_column": 380, "response_x": 551.0, "response_y": 156.0, "response_size": 85, "response_click": 1.8502627396374, "response_circle": 5.61697075259872}, "grayscale_6_other.jpg": {"subject": "31", "dataset": "Interiors Dataset", "image_height": 768, "image_width": 1024, "screen_height": 960, "screen_width": 1280, "receptive_height": 32, "receptive_width": 32, "target_found": false, "target_bbox": [202, 743, 274, 815], "X": [573.6, 530.9, 630.6, 335.7, 346.8, 518.0, 516.7, 333.3, 381.7, 365.1, 346.0, 466.0, 1023.0, 240.0], "Y": [234.1, 422.1, 566.5, 377.6, 337.8, 502.2, 529.4, 289.2, 240.9, 358.9, 586.3, 578.8, 590.8, 268.0], "T": [679, 90, 118, 218, 155, 187, 134, 162, 219, 221, 226, 190, 285], "target_object": "TBD", "max_fixations": 13, "subject_name": "JCG", "initial_fixation_row": 114, "initial_fixation_column": 443, "response_x": 240.0, "response_y": 268.0, "response_size": 85, "response_click": 3.19998357875738, "response_circle": 5.4668537513935}, "grayscale_18_opensource.jpg": {"subject": "31", "dataset": "Interiors Dataset", "image_height": 768, "image_width": 1024, "screen_height": 960, "screen_width": 1280, "receptive_height": 32, "receptive_width": 32, "target_found": true, "target_bbox": [217, 746, 289, 818], "X": [564.9, 570.6, 428.29999999999995, 760.8, 775.0], "Y": [336.8, 298.8, 219.0, 235.5, 259.0], "T": [380, 119, 128, 265], "target_object": "TBD", "max_fixations": 13, "subject_name": "JCG", "initial_fixation_row": 415, "initial_fixation_column": 463, "response_x": 775.0, "response_y": 259.0, "response_size": 21, "response_click": 1.38350223738234, "response_circle": 2.95021347596776}, "grayscale_98_oliva.jpg": {"subject": "31", "dataset": "Interiors Dataset", "image_height": 768, "image_width": 1024, "screen_height": 960, "screen_width": 1280, "receptive_height": 32, "receptive_width": 32, "target_found": false, "target_bbox": [397, 855, 469, 927], "X": [647.4, 963.3, 882.0], "Y": [413.70000000000005, 381.2, 428.0], "T": [160, 162], "target_object": "car", "max_fixations": 13, "subject_name": "JCG", "initial_fixation_row": 158, "initial_fixation_column": 661, "response_x": 882.0, "response_y": 428.0, "response_size": 19, "response_click": 1.66696195554687, "response_circle": 2.96702236222336}, "grayscale_5_opensource.jpg": {"subject": "31", "dataset": "Interiors Dataset", "image_height": 768, "image_width": 1024, "screen_height": 960, "screen_width": 1280, "receptive_height": 32, "receptive_width": 32, "target_found": false, "target_bbox": [596, 695, 668, 767], "X": [783.1, 661.6, 408.5, 700.0], "Y": [589.3, 537.5, 611.2, 632.0], "T": [213, 138, 100], "target_object": "TBD", "max_fixations": 5, "subject_name": "JCG", "initial_fixation_row": 390, "initial_fixation_column": 995, "response_x": 700.0, "response_y": 632.0, "response_size": 27, "response_click": 1.88347262050956, "response_circle": 3.51687046582811}, "grayscale_16_oliva.jpg": {"subject": "31", "dataset": "Interiors Dataset", "image_height": 768, "image_width": 1024, "screen_height": 960, "screen_width": 1280, "receptive_height": 32, "receptive_width": 32, "target_found": true, "target_bbox": [172, 677, 244, 749], "X": [836.2, 715.7, 590.5, 749.0, 716.0], "Y": [331.6, 319.2, 380.0, 162.60000000000002, 213.0], "T": [348, 235, 277, 470], "target_object": "TBD", "max_fixations": 9, "subject_name": "JCG", "initial_fixation_row": 559, "initial_fixation_column": 785, "response_x": 716.0, "response_y": 213.0, "response_size": 19, "response_click": 2.20015629485715, "response_circle": 3.60035012400476}, "grayscale_6_airbnb.jpg": {"subject": "31", "dataset": "Interiors Dataset", "image_height": 768, "image_width": 1024, "screen_height": 960, "screen_width": 1280, "receptive_height": 32, "receptive_width": 32, "target_found": true, "target_bbox": [591, 134, 663, 206], "X": [618.9, 824.6, 991.2, 974.9000000000001, 706.1, 423.4, 477.6, 727.5, 189.10000000000002, 452.1, 157.6, 220.0], "Y": [394.29999999999995, 431.5, 476.9, 203.39999999999998, 298.8, 429.1, 403.9, 426.20000000000005, 680.8, 407.29999999999995, 633.2, 607.0], "T": [167, 139, 163, 253, 118, 229, 138, 184, 156, 173, 147], "target_object": "potted plant", "max_fixations": 13, "subject_name": "JCG", "initial_fixation_row": 747, "initial_fixation_column": 507, "response_x": 220.0, "response_y": 607.0, "response_size": 25, "response_click": 1.65016186638968, "response_circle": 3.21695960965008}, "grayscale_13_kitchen.jpg": {"subject": "31", "dataset": "Interiors Dataset", "image_height": 768, "image_width": 1024, "screen_height": 960, "screen_width": 1280, "receptive_height": 32, "receptive_width": 32, "target_found": false, "target_bbox": [444, 788, 516, 860], "X": [677.7, 881.5, 834.0], "Y": [353.9, 460.70000000000005, 490.0], "T": [278, 142], "target_object": "TBD", "max_fixations": 9, "subject_name": "JCG", "initial_fixation_row": 129, "initial_fixation_column": 753, "response_x": 834.0, "response_y": 490.0, "response_size": 27, "response_click": 1.80014456546633, "response_circle": 3.26693351159338}, "grayscale_19_kitchen.jpg": {"subject": "31", "dataset": "Interiors Dataset", "image_height": 768, "image_width": 1024, "screen_height": 960, "screen_width": 1280, "receptive_height": 32, "receptive_width": 32, "target_found": false, "target_bbox": [409, 886, 481, 958], "X": [753.3, 426.20000000000005, 699.5, 978.3, 911.0], "Y": [423.1, 447.20000000000005, 282.7, 451.79999999999995, 446.0], "T": [393, 101, 74, 187], "target_object": "TBD", "max_fixations": 9, "subject_name": "JCG", "initial_fixation_row": 670, "initial_fixation_column": 644, "response_x": 911.0, "response_y": 446.0, "response_size": 37, "response_click": 1.58342218387406, "response_circle": 3.11692794010742}, "grayscale_21_opensource.jpg": {"subject": "31", "dataset": "Interiors Dataset", "image_height": 768, "image_width": 1024, "screen_height": 960, "screen_width": 1280, "receptive_height": 32, "receptive_width": 32, "target_found": false, "target_bbox": [397, 419, 469, 491], "X": [698.3, 890.7, 991.4, 962.0, 1023.0, 656.5, 681.9, 208.8, 849.2, 947.8, 841.3, 620.2, 828.0], "Y": [486.1, 451.7, 451.5, 456.2, 439.0, 606.0, 602.4, 671.7, 474.5, 452.1, 429.95000000000005, 452.8, 344.0], "T": [436, 147, 207, 131, 266, 191, 68, 226, 250, 215, 227, 268, 251], "target_object": "cup", "max_fixations": 13, "subject_name": "JCG", "initial_fixation_row": 378, "initial_fixation_column": 809, "response_x": 828.0, "response_y": 344.0, "response_size": 47, "response_click": 1.26699831680162, "response_circle": 3.56699861004017}, "grayscale_50_oliva.jpg": {"subject": "31", "dataset": "Interiors Dataset", "image_height": 768, "image_width": 1024, "screen_height": 960, "screen_width": 1280, "receptive_height": 32, "receptive_width": 32, "target_found": true, "target_bbox": [130, 471, 202, 543], "X": [799.1, 772.4, 515.0, 528.0], "Y": [275.2, 267.5, 162.8, 169.0], "T": [327, 266, 218], "target_object": "TBD", "max_fixations": 9, "subject_name": "JCG", "initial_fixation_row": 452, "initial_fixation_column": 722, "response_x": 528.0, "response_y": 169.0, "response_size": 39, "response_click": 1.48358229087899, "response_circle": 3.1169097594684}, "grayscale_29_oliva.jpg": {"subject": "31", "dataset": "Interiors Dataset", "image_height": 768, "image_width": 1024, "screen_height": 960, "screen_width": 1280, "receptive_height": 32, "receptive_width": 32, "target_found": false, "target_bbox": [328, 874, 400, 946], "X": [710.7, 708.1, 508.9, 529.1, 541.6, 517.1, 986.5, 1023.0, 904.0], "Y": [602.7, 397.0, 346.5, 292.0, 379.6, 389.4, 440.3, 464.3, 349.0], "T": [648, 209, 146, 145, 131, 226, 280, 412], "target_object": "TBD", "max_fixations": 9, "subject_name": "JCG", "initial_fixation_row": 493, "initial_fixation_column": 576, "response_x": 904.0, "response_y": 349.0, "response_size": 21, "response_click": 1.83354739577044, "response_circle": 3.13361366715981}, "grayscale_13_opensource.jpg": {"subject": "31", "dataset": "Interiors Dataset", "image_height": 768, "image_width": 1024, "screen_height": 960, "screen_width": 1280, "receptive_height": 32, "receptive_width": 32, "target_found": true, "target_bbox": [399, 833, 471, 905], "X": [745.9, 902.0, 893.0], "Y": [340.0, 431.1, 441.0], "T": [427, 301], "target_object": "TBD", "max_fixations": 5, "subject_name": "JCG", "initial_fixation_row": 412, "initial_fixation_column": 512, "response_x": 893.0, "response_y": 441.0, "response_size": 21, "response_click": 2.00021142326295, "response_circle": 3.66684466099832}, "grayscale_58_oliva.jpg": {"subject": "31", "dataset": "Interiors Dataset", "image_height": 768, "image_width": 1024, "screen_height": 960, "screen_width": 1280, "receptive_height": 32, "receptive_width": 32, "target_found": true, "target_bbox": [311, 939, 383, 1011], "X": [656.9, 826.1, 972.4000000000001, 968.0], "Y": [363.7, 387.1, 332.0, 345.0], "T": [463, 104, 257], "target_object": "bowl", "max_fixations": 5, "subject_name": "JCG", "initial_fixation_row": 10, "initial_fixation_column": 854, "response_x": 968.0, "response_y": 345.0, "response_size": 19, "response_click": 0.933514553296845, "response_circle": 2.26686724019237}, "grayscale_28_oliva.jpg": {"subject": "31", "dataset": "Interiors Dataset", "image_height": 768, "image_width": 1024, "screen_height": 960, "screen_width": 1280, "receptive_height": 32, "receptive_width": 32, "target_found": true, "target_bbox": [494, 826, 566, 898], "X": [528.2, 818.3, 852.0], "Y": [401.79999999999995, 478.1, 530.0], "T": [140, 209, 312, 147, 201], "target_object": "cup", "max_fixations": 13, "subject_name": "JCG", "initial_fixation_row": 511, "initial_fixation_column": 504, "response_x": 852.0, "response_y": 530.0, "response_size": 19, "response_click": 1.95023810782004, "response_circle": 3.3503914703615}, "grayscale_4_oliva.jpg": {"subject": "31", "dataset": "Interiors Dataset", "image_height": 768, "image_width": 1024, "screen_height": 960, "screen_width": 1280, "receptive_height": 32, "receptive_width": 32, "target_found": true, "target_bbox": [69, 332, 141, 404], "X": [296.2, 454.20000000000005, 562.9, 786.7, 390.9, 380.0], "Y": [422.6, 366.6, 187.2, 247.2, 151.89999999999998, 121.0], "T": [324, 138, 208, 127, 220, 141], "target_object": "potted plant", "max_fixations": 9, "subject_name": "JCG", "initial_fixation_row": 224, "initial_fixation_column": 706, "response_x": 380.0, "response_y": 121.0, "response_size": 23, "response_click": 1.45021875418024, "response_circle": 2.8168068335508}, "grayscale_45_oliva.jpg": {"subject": "31", "dataset": "Interiors Dataset", "image_height": 768, "image_width": 1024, "screen_height": 960, "screen_width": 1280, "receptive_height": 32, "receptive_width": 32, "target_found": true, "target_bbox": [658, 418, 730, 490], "X": [500.1, 757.0, 434.5, 287.1, 226.60000000000002, 722.1, 824.3, 946.8, 464.1, 423.79999999999995, 504.29999999999995, 458.0], "Y": [381.0, 400.9, 492.6, 634.0, 603.0, 342.5, 296.6, 301.4, 477.79999999999995, 447.4, 700.4, 679.0], "T": [490, 102, 99, 156, 186, 147, 345, 93, 164, 168, 193], "target_object": "TBD", "max_fixations": 13, "subject_name": "JCG", "initial_fixation_row": 584, "initial_fixation_column": 113, "response_x": 458.0, "response_y": 679.0, "response_size": 19, "response_click": 1.26682618720224, "response_circle": 2.73357408028096}, "grayscale_68_oliva.jpg": {"subject": "31", "dataset": "Interiors Dataset", "image_height": 768, "image_width": 1024, "screen_height": 960, "screen_width": 1280, "receptive_height": 32, "receptive_width": 32, "target_found": true, "target_bbox": [565, 935, 637, 1007], "X": [607.0, 476.0, 873.8, 952.85, 1023.0, 882.0], "Y": [381.5, 327.8, 470.20000000000005, 537.3, 572.5, 541.0], "T": [574, 143, 162, 238, 137, 189], "target_object": "TBD", "max_fixations": 9, "subject_name": "JCG", "initial_fixation_row": 277, "initial_fixation_column": 819, "response_x": 882.0, "response_y": 541.0, "response_size": 51, "response_click": 1.61674730660161, "response_circle": 3.78375530021731}, "grayscale_4_other.jpg": {"subject": "31", "dataset": "Interiors Dataset", "image_height": 768, "image_width": 1024, "screen_height": 960, "screen_width": 1280, "receptive_height": 32, "receptive_width": 32, "target_found": false, "target_bbox": [324, 180, 396, 252], "X": [741.7, 515.6, 682.4, 178.39999999999998, 66.69999999999999, 147.8, 177.0, 290.9, 256.85, 288.4, 219.0], "Y": [355.6, 377.0, 414.79999999999995, 419.6, 423.0, 559.8, 638.3, 323.1, 289.8, 315.2, 338.0], "T": [236, 165, 217, 291, 238, 291, 241, 292, 688, 1064, 85], "target_object": "cup", "max_fixations": 13, "subject_name": "JCG", "initial_fixation_row": 39, "initial_fixation_column": 57, "response_x": 219.0, "response_y": 338.0, "response_size": 21, "response_click": 1.16709273890592, "response_circle": 2.56709537800634}, "grayscale_52_oliva.jpg": {"subject": "31", "dataset": "Interiors Dataset", "image_height": 768, "image_width": 1024, "screen_height": 960, "screen_width": 1280, "receptive_height": 32, "receptive_width": 32, "target_found": false, "target_bbox": [424, 74, 496, 146], "X": [596.2, 494.7, 849.8, 386.8, 133.0], "Y": [555.4, 552.5, 543.2, 547.0, 455.0], "T": [240, 152, 294, 741], "target_object": "TBD", "max_fixations": 5, "subject_name": "JCG", "initial_fixation_row": 108, "initial_fixation_column": 177, "response_x": 133.0, "response_y": 455.0, "response_size": 27, "response_click": 1.45034044724889, "response_circle": 2.6503131762729}, "grayscale_4_housebeautiful.jpg": {"subject": "31", "dataset": "Interiors Dataset", "image_height": 768, "image_width": 1024, "screen_height": 960, "screen_width": 1280, "receptive_height": 32, "receptive_width": 32, "target_found": false, "target_bbox": [622, 113, 694, 185], "X": [772.9, 746.3, 615.3, 910.7, 808.4, 816.9, 952.05, 623.0, 639.5, 599.6, 634.8, 618.9, 592.2, 734.0], "Y": [450.5, 450.0, 510.9, 635.8, 561.7, 606.8, 440.6, 432.2, 451.9, 447.7, 370.5, 576.9, 581.7, 390.0], "T": [761, 259, 272, 222, 237, 198, 327, 122, 181, 140, 176, 167, 303, 99], "target_object": "cup", "max_fixations": 13, "subject_name": "JCG", "initial_fixation_row": 645, "initial_fixation_column": 507, "response_x": 734.0, "response_y": 390.0, "response_size": 33, "response_click": 3.25022491218988, "response_circle": 4.75035510904854}, "grayscale_84_oliva.jpg": {"subject": "31", "dataset": "Interiors Dataset", "image_height": 768, "image_width": 1024, "screen_height": 960, "screen_width": 1280, "receptive_height": 32, "receptive_width": 32, "target_found": false, "target_bbox": [263, 746, 335, 818], "X": [611.4, 391.6, 260.0], "Y": [495.9, 596.2, 479.0], "T": [285, 838], "target_object": "chair", "max_fixations": 3, "subject_name": "JCG", "initial_fixation_row": 511, "initial_fixation_column": 493, "response_x": 260.0, "response_y": 479.0, "response_size": 23, "response_click": 1.88345649256371, "response_circle": 3.21687046583975}, "grayscale_20_housebeautiful.jpg": {"subject": "31", "dataset": "Interiors Dataset", "image_height": 768, "image_width": 1024, "screen_height": 960, "screen_width": 1280, "receptive_height": 32, "receptive_width": 32, "target_found": true, "target_bbox": [435, 656, 507, 728], "X": [620.9, 720.6, 694.0], "Y": [400.9, 483.6, 466.0], "T": [536, 562], "target_object": "TBD", "max_fixations": 9, "subject_name": "JCG", "initial_fixation_row": 167, "initial_fixation_column": 880, "response_x": 694.0, "response_y": 466.0, "response_size": 21, "response_click": 1.26688131556148, "response_circle": 2.43366586323828}, "grayscale_7_housebeautiful.jpg": {"subject": "31", "dataset": "Interiors Dataset", "image_height": 768, "image_width": 1024, "screen_height": 960, "screen_width": 1280, "receptive_height": 32, "receptive_width": 32, "target_found": false, "target_bbox": [452, 500, 524, 572], "X": [651.6, 695.6, 367.2, 219.9, 1023.0, 117.0], "Y": [525.8, 520.6, 679.7, 709.0, 664.75, 563.0], "T": [916, 151, 173, 327, 262, 178], "target_object": "bowl", "max_fixations": 5, "subject_name": "JCG", "initial_fixation_row": 275, "initial_fixation_column": 248, "response_x": 117.0, "response_y": 563.0, "response_size": 41, "response_click": 1.16685463109752, "response_circle": 2.86676578054903}, "grayscale_12_housebeautiful.jpg": {"subject": "31", "dataset": "Interiors Dataset", "image_height": 768, "image_width": 1024, "screen_height": 960, "screen_width": 1280, "receptive_height": 32, "receptive_width": 32, "target_found": false, "target_bbox": [418, 740, 490, 812], "X": [534.0, 378.3, 424.2, 893.1, 768.0], "Y": [534.6, 594.8, 629.5, 604.9, 446.0], "T": [242, 320, 108, 287], "target_object": "potted plant", "max_fixations": 5, "subject_name": "JCG", "initial_fixation_row": 333, "initial_fixation_column": 439, "response_x": 768.0, "response_y": 446.0, "response_size": 21, "response_click": 1.15017506206641, "response_circle": 2.3502342957654}, "grayscale_13_other.jpg": {"subject": "31", "dataset": "Interiors Dataset", "image_height": 768, "image_width": 1024, "screen_height": 960, "screen_width": 1280, "receptive_height": 32, "receptive_width": 32, "target_found": false, "target_bbox": [322, 735, 394, 807], "X": [654.8, 562.7, 691.0, 486.4, 792.9, 908.1, 873.3, 920.7, 451.5, 224.8, 570.7, 525.7, 546.4, 991.8, 773.0], "Y": [509.6, 463.7, 428.6, 457.1, 525.8, 578.4, 598.3, 697.7, 510.1, 510.0, 474.0, 473.1, 473.3, 610.6, 378.0], "T": [920, 137, 197, 77, 175, 194, 132, 152, 225, 324, 129, 272, 151, 100], "target_object": "TBD", "max_fixations": 13, "subject_name": "JCG", "initial_fixation_row": 138, "initial_fixation_column": 488, "response_x": 773.0, "response_y": 378.0, "response_size": 87, "response_click": 1.60031493572751, "response_circle": 3.76688864652533}, "grayscale_60_oliva.jpg": {"subject": "31", "dataset": "Interiors Dataset", "image_height": 768, "image_width": 1024, "screen_height": 960, "screen_width": 1280, "receptive_height": 32, "receptive_width": 32, "target_found": true, "target_bbox": [0, 219, 72, 291], "X": [597.8, 439.20000000000005, 825.7, 131.2, 102.80000000000001, 280.0, 292.4, 283.4, 107.6, 104.19999999999999, 368.3, 301.9, 251.0], "Y": [294.8, 320.9, 295.8, 307.3, 290.2, 472.6, 521.9, 651.0, 120.9, 85.6, 0, 0, 40.0], "T": [502, 109, 268, 152, 158, 341, 304, 172, 199, 96, 113, 455], "target_object": "TBD", "max_fixations": 13, "subject_name": "JCG", "initial_fixation_row": 211, "initial_fixation_column": 567, "response_x": 251.0, "response_y": 40.0, "response_size": 23, "response_click": 1.48359490005532, "response_circle": 2.65021582186455}, "grayscale_99_oliva.jpg": {"subject": "31", "dataset": "Interiors Dataset", "image_height": 768, "image_width": 1024, "screen_height": 960, "screen_width": 1280, "receptive_height": 32, "receptive_width": 32, "target_found": false, "target_bbox": [566, 715, 638, 787], "X": [729.5, 857.6, 107.0], "Y": [231.5, 181.1, 365.0], "T": [456, 452], "target_object": "TBD", "max_fixations": 3, "subject_name": "JCG", "initial_fixation_row": 364, "initial_fixation_column": 1019, "response_x": 107.0, "response_y": 365.0, "response_size": 61, "response_click": 3.53355355374515, "response_circle": 5.43351631273981}, "grayscale_63_oliva.jpg": {"subject": "31", "dataset": "Interiors Dataset", "image_height": 768, "image_width": 1024, "screen_height": 960, "screen_width": 1280, "receptive_height": 32, "receptive_width": 32, "target_found": false, "target_bbox": [321, 699, 393, 771], "X": [806.2, 997.3, 871.2, 553.6, 271.1, 394.2, 888.9, 858.9, 723.0], "Y": [409.9, 423.1, 443.2, 471.9, 505.0, 523.3, 510.3, 494.0, 369.0], "T": [254, 49, 301, 203, 161, 169, 177, 251], "target_object": "TBD", "max_fixations": 9, "subject_name": "JCG", "initial_fixation_row": 696, "initial_fixation_column": 849, "response_x": 723.0, "response_y": 369.0, "response_size": 13, "response_click": 1.28342394332867, "response_circle": 3.28366732934956}, "grayscale_70_oliva.jpg": {"subject": "31", "dataset": "Interiors Dataset", "image_height": 768, "image_width": 1024, "screen_height": 960, "screen_width": 1280, "receptive_height": 32, "receptive_width": 32, "target_found": false, "target_bbox": [370, 807, 442, 879], "X": [652.2, 889.9, 988.0, 850.0], "Y": [478.5, 482.8, 472.6, 404.0], "T": [663, 191, 136], "target_object": "TBD", "max_fixations": 3, "subject_name": "JCG", "initial_fixation_row": 764, "initial_fixation_column": 828, "response_x": 850.0, "response_y": 404.0, "response_size": 17, "response_click": 1.73364064487396, "response_circle": 3.16695139900548}, "grayscale_27_opensource.jpg": {"subject": "31", "dataset": "Interiors Dataset", "image_height": 768, "image_width": 1024, "screen_height": 960, "screen_width": 1280, "receptive_height": 32, "receptive_width": 32, "target_found": false, "target_bbox": [375, 440, 447, 512], "X": [471.0, 514.0, 480.0], "Y": [327.3, 352.1, 414.0], "T": [1150, 731], "target_object": "TBD", "max_fixations": 13, "subject_name": "JCG", "initial_fixation_row": 534, "initial_fixation_column": 812, "response_x": 480.0, "response_y": 414.0, "response_size": 19, "response_click": 1.28356235084357, "response_circle": 2.48355853877729}, "grayscale_6_housebeautiful.jpg": {"subject": "31", "dataset": "Interiors Dataset", "image_height": 768, "image_width": 1024, "screen_height": 960, "screen_width": 1280, "receptive_height": 32, "receptive_width": 32, "target_found": true, "target_bbox": [536, 915, 608, 987], "X": [594.2, 631.4, 790.6, 158.6, 385.5, 576.5, 957.0, 946.0], "Y": [330.6, 520.2, 547.1, 572.8, 567.0, 564.9, 551.8, 559.0], "T": [622, 141, 111, 322, 189, 403, 226], "target_object": "TBD", "max_fixations": 13, "subject_name": "JCG", "initial_fixation_row": 226, "initial_fixation_column": 860, "response_x": 946.0, "response_y": 559.0, "response_size": 21, "response_click": 1.10005835397169, "response_circle": 1.80026801786153}, "grayscale_47_oliva.jpg": {"subject": "31", "dataset": "Interiors Dataset", "image_height": 768, "image_width": 1024, "screen_height": 960, "screen_width": 1280, "receptive_height": 32, "receptive_width": 32, "target_found": false, "target_bbox": [391, 739, 463, 811], "X": [619.2, 809.6, 978.0], "Y": [356.2, 371.7, 467.0], "T": [292, 194], "target_object": "TBD", "max_fixations": 13, "subject_name": "JCG", "initial_fixation_row": 151, "initial_fixation_column": 547, "response_x": 978.0, "response_y": 467.0, "response_size": 29, "response_click": 2.93374591669999, "response_circle": 3.60066945827566}, "grayscale_34_oliva.jpg": {"subject": "31", "dataset": "Interiors Dataset", "image_height": 768, "image_width": 1024, "screen_height": 960, "screen_width": 1280, "receptive_height": 32, "receptive_width": 32, "target_found": true, "target_bbox": [618, 126, 690, 198], "X": [731.7, 525.0, 186.0, 175.2, 148.0], "Y": [441.29999999999995, 409.6, 581.8, 661.3, 649.0], "T": [266, 124, 140, 170], "target_object": "TBD", "max_fixations": 9, "subject_name": "JCG", "initial_fixation_row": 324, "initial_fixation_column": 301, "response_x": 148.0, "response_y": 649.0, "response_size": 23, "response_click": 1.48319991084281, "response_circle": 2.11694700049702}, "grayscale_54_oliva.jpg": {"subject": "31", "dataset": "Interiors Dataset", "image_height": 768, "image_width": 1024, "screen_height": 960, "screen_width": 1280, "receptive_height": 32, "receptive_width": 32, "target_found": false, "target_bbox": [310, 864, 382, 936], "X": [627.5, 708.4, 848.3, 680.4, 548.0], "Y": [479.6, 470.5, 411.2, 417.0, 325.0], "T": [237, 259, 184, 790], "target_object": "potted plant", "max_fixations": 5, "subject_name": "JCG", "initial_fixation_row": 237, "initial_fixation_column": 559, "response_x": 548.0, "response_y": 325.0, "response_size": 19, "response_click": 1.28312513564015, "response_circle": 1.8835330271977}, "grayscale_9_kitchen.jpg": {"subject": "31", "dataset": "Interiors Dataset", "image_height": 768, "image_width": 1024, "screen_height": 960, "screen_width": 1280, "receptive_height": 32, "receptive_width": 32, "target_found": false, "target_bbox": [146, 92, 218, 164], "X": [540.2, 720.4, 174.0], "Y": [445.9, 423.8, 323.0], "T": [499, 389], "target_object": "TBD", "max_fixations": 3, "subject_name": "JCG", "initial_fixation_row": 526, "initial_fixation_column": 228, "response_x": 174.0, "response_y": 323.0, "response_size": 99, "response_click": 2.550198227691, "response_circle": 4.35029998060782}, "grayscale_15_kitchen.jpg": {"subject": "31", "dataset": "Interiors Dataset", "image_height": 768, "image_width": 1024, "screen_height": 960, "screen_width": 1280, "receptive_height": 32, "receptive_width": 32, "target_found": true, "target_bbox": [270, 894, 342, 966], "X": [549.3, 617.4, 761.4, 911.6, 915.0], "Y": [328.4, 309.8, 310.4, 315.7, 298.0], "T": [908, 210, 177, 175], "target_object": "TBD", "max_fixations": 9, "subject_name": "JCG", "initial_fixation_row": 661, "initial_fixation_column": 978, "response_x": 915.0, "response_y": 298.0, "response_size": 23, "response_click": 1.2335101547651, "response_circle": 1.86668250139337}, "grayscale_3_oliva.jpg": {"subject": "31", "dataset": "Interiors Dataset", "image_height": 768, "image_width": 1024, "screen_height": 960, "screen_width": 1280, "receptive_height": 32, "receptive_width": 32, "target_found": true, "target_bbox": [336, 741, 408, 813], "X": [622.4, 653.8, 828.9, 769.0], "Y": [341.3, 368.4, 337.1, 366.0], "T": [720, 115, 242], "target_object": "TBD", "max_fixations": 13, "subject_name": "JCG", "initial_fixation_row": 85, "initial_fixation_column": 991, "response_x": 769.0, "response_y": 366.0, "response_size": 17, "response_click": 1.30019441561308, "response_circle": 1.86695315846009}, "grayscale_10_oliva.jpg": {"subject": "31", "dataset": "Interiors Dataset", "image_height": 768, "image_width": 1024, "screen_height": 960, "screen_width": 1280, "receptive_height": 32, "receptive_width": 32, "target_found": false, "target_bbox": [310, 0, 382, 72], "X": [648.0, 663.6, 844.9, 512.0], "Y": [489.5, 533.4, 595.6, 330.0], "T": [464, 223, 520], "target_object": "TBD", "max_fixations": 3, "subject_name": "JCG", "initial_fixation_row": 640, "initial_fixation_column": 240, "response_x": 512.0, "response_y": 330.0, "response_size": 27, "response_click": 2.08351308712736, "response_circle": 2.65015805431176}, "grayscale_20_oliva.jpg": {"subject": "31", "dataset": "Interiors Dataset", "image_height": 768, "image_width": 1024, "screen_height": 960, "screen_width": 1280, "receptive_height": 32, "receptive_width": 32, "target_found": true, "target_bbox": [204, 48, 276, 120], "X": [586.8, 538.1, 360.0, 228.39999999999998, 122.19999999999999, 87.0], "Y": [353.1, 345.4, 298.1, 282.4, 252.3, 235.0], "T": [670, 180, 155, 137, 144], "target_object": "TBD", "max_fixations": 9, "subject_name": "JCG", "initial_fixation_row": 32, "initial_fixation_column": 375, "response_x": 87.0, "response_y": 235.0, "response_size": 19, "response_click": 1.13338787527755, "response_circle": 1.60026449902216}, "grayscale_8_housebeautiful.jpg": {"subject": "31", "dataset": "Interiors Dataset", "image_height": 768, "image_width": 1024, "screen_height": 960, "screen_width": 1280, "receptive_height": 32, "receptive_width": 32, "target_found": false, "target_bbox": [236, 620, 308, 692], "X": [529.4, 530.6, 548.9, 295.4, 331.5, 882.9, 937.0, 1021.1, 881.0], "Y": [417.3, 517.0, 476.0, 353.1, 695.8, 658.6, 696.0, 696.1, 450.0], "T": [497, 189, 129, 292, 235, 317, 186, 145], "target_object": "TBD", "max_fixations": 9, "subject_name": "JCG", "initial_fixation_row": 503, "initial_fixation_column": 929, "response_x": 881.0, "response_y": 450.0, "response_size": 43, "response_click": 1.46669540385483, "response_circle": 2.83348757558269}, "grayscale_2_housebeautiful.jpg": {"subject": "31", "dataset": "Interiors Dataset", "image_height": 768, "image_width": 1024, "screen_height": 960, "screen_width": 1280, "receptive_height": 32, "receptive_width": 32, "target_found": true, "target_bbox": [499, 447, 571, 519], "X": [549.8, 468.0, 554.2, 531.7, 484.0], "Y": [329.3, 414.1, 304.4, 507.29999999999995, 524.0], "T": [1618, 209, 175, 123], "target_object": "bowl", "max_fixations": 13, "subject_name": "JCG", "initial_fixation_row": 471, "initial_fixation_column": 835, "response_x": 484.0, "response_y": 524.0, "response_size": 15, "response_click": 1.20030496560503, "response_circle": 1.8335966594168}, "grayscale_15_opensource.jpg": {"subject": "31", "dataset": "Interiors Dataset", "image_height": 768, "image_width": 1024, "screen_height": 960, "screen_width": 1280, "receptive_height": 32, "receptive_width": 32, "target_found": true, "target_bbox": [326, 401, 398, 473], "X": [722.7, 619.3, 455.6, 446.0], "Y": [504.0, 402.4, 391.9, 351.0], "T": [379, 96, 279, 177, 223, 704, 239, 389], "target_object": "bowl", "max_fixations": 9, "subject_name": "JCG", "initial_fixation_row": 626, "initial_fixation_column": 195, "response_x": 446.0, "response_y": 351.0, "response_size": 17, "response_click": 1.66671035886975, "response_circle": 2.46696547436295}, "grayscale_38_oliva.jpg": {"subject": "31", "dataset": "Interiors Dataset", "image_height": 768, "image_width": 1024, "screen_height": 960, "screen_width": 1280, "receptive_height": 32, "receptive_width": 32, "target_found": true, "target_bbox": [211, 485, 283, 557], "X": [608.6, 297.5, 172.3, 109.19999999999999, 782.0, 537.6, 513.0], "Y": [352.0, 484.6, 394.5, 440.20000000000005, 317.8, 264.0, 247.0], "T": [408, 170, 148, 82, 253, 157], "target_object": "TBD", "max_fixations": 9, "subject_name": "JCG", "initial_fixation_row": 239, "initial_fixation_column": 163, "response_x": 513.0, "response_y": 247.0, "response_size": 19, "response_click": 1.58351279387716, "response_circle": 2.25009588821558}, "grayscale_17_opensource.jpg": {"subject": "31", "dataset": "Interiors Dataset", "image_height": 768, "image_width": 1024, "screen_height": 960, "screen_width": 1280, "receptive_height": 32, "receptive_width": 32, "target_found": true, "target_bbox": [314, 822, 386, 894], "X": [587.1, 610.4, 288.5, 894.6, 855.0], "Y": [334.9, 428.1, 425.6, 337.4, 345.0], "T": [300, 140, 122, 525], "target_object": "potted plant", "max_fixations": 13, "subject_name": "JCG", "initial_fixation_row": 707, "initial_fixation_column": 886, "response_x": 855.0, "response_y": 345.0, "response_size": 17, "response_click": 1.44991378852865, "response_circle": 2.11697104584891}, "grayscale_89_oliva.jpg": {"subject": "31", "dataset": "Interiors Dataset", "image_height": 768, "image_width": 1024, "screen_height": 960, "screen_width": 1280, "receptive_height": 32, "receptive_width": 32, "target_found": true, "target_bbox": [98, 423, 170, 495], "X": [516.6, 581.0, 478.70000000000005, 466.0], "Y": [317.7, 253.7, 154.8, 123.0], "T": [298, 204, 182], "target_object": "TBD", "max_fixations": 13, "subject_name": "JCG", "initial_fixation_row": 381, "initial_fixation_column": 200, "response_x": 466.0, "response_y": 123.0, "response_size": 17, "response_click": 0.916829412744846, "response_circle": 1.45045070402557}, "grayscale_11_kitchen.jpg": {"subject": "31", "dataset": "Interiors Dataset", "image_height": 768, "image_width": 1024, "screen_height": 960, "screen_width": 1280, "receptive_height": 32, "receptive_width": 32, "target_found": true, "target_bbox": [319, 135, 391, 207], "X": [591.5, 437.0, 218.10000000000002, 166.0], "Y": [371.1, 302.3, 314.8, 363.0], "T": [434, 227, 281, 538], "target_object": "TBD", "max_fixations": 5, "subject_name": "JCG", "initial_fixation_row": 389, "initial_fixation_column": 527, "response_x": 166.0, "response_y": 363.0, "response_size": 21, "response_click": 0.866813284752425, "response_circle": 2.73336177726742}, "grayscale_18_oliva.jpg": {"subject": "31", "dataset": "Interiors Dataset", "image_height": 768, "image_width": 1024, "screen_height": 960, "screen_width": 1280, "receptive_height": 32, "receptive_width": 32, "target_found": false, "target_bbox": [381, 647, 453, 719], "X": [580.7, 583.85, 762.2, 155.0], "Y": [496.6, 522.35, 385.9, 156.0], "T": [459, 305, 182, 400], "target_object": "TBD", "max_fixations": 5, "subject_name": "JCG", "initial_fixation_row": 727, "initial_fixation_column": 861, "response_x": 155.0, "response_y": 156.0, "response_size": 43, "response_click": 3.59989560791291, "response_circle": 4.56703614431899}, "grayscale_61_oliva.jpg": {"subject": "31", "dataset": "Interiors Dataset", "image_height": 768, "image_width": 1024, "screen_height": 960, "screen_width": 1280, "receptive_height": 32, "receptive_width": 32, "target_found": true, "target_bbox": [80, 159, 152, 231], "X": [682.1, 424.4, 1001.5, 1023.0, 965.0, 226.10000000000002, 208.0], "Y": [344.1, 347.0, 391.4, 323.1, 165.7, 132.5, 124.0], "T": [242, 170, 194, 88, 130, 206], "target_object": "bowl", "max_fixations": 9, "subject_name": "JCG", "initial_fixation_row": 190, "initial_fixation_column": 545, "response_x": 208.0, "response_y": 124.0, "response_size": 15, "response_click": 0.900193242705427, "response_circle": 1.40025071694981}, "grayscale_14_airbnb.jpg": {"subject": "31", "dataset": "Interiors Dataset", "image_height": 768, "image_width": 1024, "screen_height": 960, "screen_width": 1280, "receptive_height": 32, "receptive_width": 32, "target_found": true, "target_bbox": [256, 77, 328, 149], "X": [561.3, 381.9, 549.3, 711.3, 735.2, 205.7, 158.5, 107.0], "Y": [332.6, 330.2, 556.2, 375.0, 252.60000000000002, 257.3, 245.10000000000002, 308.0], "T": [252, 164, 186, 239, 138, 154, 119], "target_object": "TBD", "max_fixations": 13, "subject_name": "JCG", "initial_fixation_row": 52, "initial_fixation_column": 379, "response_x": 107.0, "response_y": 308.0, "response_size": 19, "response_click": 1.40013664809521, "response_circle": 1.93343186069978}, "grayscale_6_oliva.jpg": {"subject": "31", "dataset": "Interiors Dataset", "image_height": 768, "image_width": 1024, "screen_height": 960, "screen_width": 1280, "receptive_height": 32, "receptive_width": 32, "target_found": true, "target_bbox": [175, 595, 247, 667], "X": [636.6, 664.7, 622.0], "Y": [273.1, 176.0, 210.0], "T": [281, 551], "target_object": "TBD", "max_fixations": 13, "subject_name": "JCG", "initial_fixation_row": 455, "initial_fixation_column": 893, "response_x": 622.0, "response_y": 210.0, "response_size": 17, "response_click": 1.60027857439127, "response_circle": 2.2003683046787}, "grayscale_56_oliva.jpg": {"subject": "31", "dataset": "Interiors Dataset", "image_height": 768, "image_width": 1024, "screen_height": 960, "screen_width": 1280, "receptive_height": 32, "receptive_width": 32, "target_found": false, "target_bbox": [358, 725, 430, 797], "X": [583.4, 638.7, 327.8, 204.10000000000002, 116.6, 597.4, 871.1, 596.4, 861.1, 798.8, 767.0], "Y": [376.8, 337.4, 391.29999999999995, 435.9, 417.29999999999995, 558.9, 354.1, 589.1, 339.6, 334.9, 388.0], "T": [554, 124, 328, 112, 169, 340, 137, 229, 234, 555], "target_object": "bottle", "max_fixations": 13, "subject_name": "JCG", "initial_fixation_row": 682, "initial_fixation_column": 548, "response_x": 767.0, "response_y": 388.0, "response_size": 17, "response_click": 1.01689978945069, "response_circle": 1.58357437350787}, "grayscale_53_oliva.jpg": {"subject": "31", "dataset": "Interiors Dataset", "image_height": 768, "image_width": 1024, "screen_height": 960, "screen_width": 1280, "receptive_height": 32, "receptive_width": 32, "target_found": false, "target_bbox": [242, 859, 314, 931], "X": [692.0, 509.8, 710.6, 568.0, 73.0], "Y": [419.8, 408.9, 595.0, 544.9, 391.0], "T": [1747, 177, 203, 423], "target_object": "cup", "max_fixations": 3, "subject_name": "JCG", "initial_fixation_row": 307, "initial_fixation_column": 538, "response_x": 73.0, "response_y": 391.0, "response_size": 39, "response_click": 2.55021758127259, "response_circle": 3.45029440918006}, "grayscale_33_oliva.jpg": {"subject": "31", "dataset": "Interiors Dataset", "image_height": 768, "image_width": 1024, "screen_height": 960, "screen_width": 1280, "receptive_height": 32, "receptive_width": 32, "target_found": true, "target_bbox": [357, 72, 429, 144], "X": [527.5, 247.89999999999998, 173.60000000000002, 156.1, 125.0], "Y": [290.9, 382.0, 354.1, 351.7, 397.0], "T": [1224, 177, 222, 505], "target_object": "cup", "max_fixations": 9, "subject_name": "JCG", "initial_fixation_row": 276, "initial_fixation_column": 446, "response_x": 125.0, "response_y": 397.0, "response_size": 21, "response_click": 1.28315973747522, "response_circle": 1.81692295509856}, "grayscale_5_oliva.jpg": {"subject": "31", "dataset": "Interiors Dataset", "image_height": 768, "image_width": 1024, "screen_height": 960, "screen_width": 1280, "receptive_height": 32, "receptive_width": 32, "target_found": false, "target_bbox": [120, 566, 192, 638], "X": [583.9, 707.2, 624.9, 637.2, 569.5, 269.4, 480.0], "Y": [458.1, 283.5, 268.4, 227.0, 326.1, 560.8, 149.0], "T": [212, 179, 160, 124, 203, 421], "target_object": "TBD", "max_fixations": 9, "subject_name": "JCG", "initial_fixation_row": 142, "initial_fixation_column": 960, "response_x": 480.0, "response_y": 149.0, "response_size": 91, "response_click": 2.53372451046016, "response_circle": 4.36727044003783}, "grayscale_34_housebeautiful.jpg": {"subject": "31", "dataset": "Interiors Dataset", "image_height": 768, "image_width": 1024, "screen_height": 960, "screen_width": 1280, "receptive_height": 32, "receptive_width": 32, "target_found": true, "target_bbox": [338, 74, 410, 146], "X": [539.1, 403.7, 201.60000000000002, 114.9, 111.0], "Y": [381.4, 372.3, 348.3, 352.3, 370.0], "T": [541, 74, 168, 245], "target_object": "TBD", "max_fixations": 13, "subject_name": "JCG", "initial_fixation_row": 127, "initial_fixation_column": 369, "response_x": 111.0, "response_y": 370.0, "response_size": 21, "response_click": 1.31684612721438, "response_circle": 1.95037035737187}, "grayscale_24_oliva.jpg": {"subject": "31", "dataset": "Interiors Dataset", "image_height": 768, "image_width": 1024, "screen_height": 960, "screen_width": 1280, "receptive_height": 32, "receptive_width": 32, "target_found": false, "target_bbox": [345, 3, 417, 75], "X": [574.6, 372.6, 248.0, 53.0], "Y": [393.1, 398.8, 415.5, 368.0], "T": [438, 145, 677], "target_object": "TBD", "max_fixations": 3, "subject_name": "JCG", "initial_fixation_row": 69, "initial_fixation_column": 215, "response_x": 53.0, "response_y": 368.0, "response_size": 23, "response_click": 1.35001436853781, "response_circle": 2.18353683926398}, "grayscale_7_kitchen.jpg": {"subject": "31", "dataset": "Interiors Dataset", "image_height": 768, "image_width": 1024, "screen_height": 960, "screen_width": 1280, "receptive_height": 32, "receptive_width": 32, "target_found": true, "target_bbox": [74, 629, 146, 701], "X": [552.6, 643.4, 685.0, 656.0], "Y": [231.60000000000002, 184.8, 132.10000000000002, 106.0], "T": [486, 219, 142], "target_object": "TBD", "max_fixations": 13, "subject_name": "JCG", "initial_fixation_row": 454, "initial_fixation_column": 765, "response_x": 656.0, "response_y": 106.0, "response_size": 17, "response_click": 0.94990029965993, "response_circle": 1.4835485687363}, "grayscale_49_oliva.jpg": {"subject": "31", "dataset": "Interiors Dataset", "image_height": 768, "image_width": 1024, "screen_height": 960, "screen_width": 1280, "receptive_height": 32, "receptive_width": 32, "target_found": true, "target_bbox": [301, 794, 373, 866], "X": [586.1, 600.8, 776.0, 734.9, 852.2, 818.0], "Y": [383.9, 292.2, 279.4, 274.3, 286.1, 323.0], "T": [531, 153, 169, 287, 1300], "target_object": "TBD", "max_fixations": 9, "subject_name": "JCG", "initial_fixation_row": 641, "initial_fixation_column": 1020, "response_x": 818.0, "response_y": 323.0, "response_size": 23, "response_click": 1.03358551644487, "response_circle": 1.8000266844756}, "grayscale_32_opensource.jpg": {"subject": "31", "dataset": "Interiors Dataset", "image_height": 768, "image_width": 1024, "screen_height": 960, "screen_width": 1280, "receptive_height": 32, "receptive_width": 32, "target_found": true, "target_bbox": [440, 757, 512, 829], "X": [598.6, 695.1, 835.2, 789.0], "Y": [329.3, 521.0, 433.20000000000005, 485.0], "T": [541, 171, 1379], "target_object": "TBD", "max_fixations": 13, "subject_name": "JCG", "initial_fixation_row": 127, "initial_fixation_column": 874, "response_x": 789.0, "response_y": 485.0, "response_size": 15, "response_click": 1.73358082468621, "response_circle": 2.4002703637816}, "grayscale_75_oliva.jpg": {"subject": "31", "dataset": "Interiors Dataset", "image_height": 768, "image_width": 1024, "screen_height": 960, "screen_width": 1280, "receptive_height": 32, "receptive_width": 32, "target_found": true, "target_bbox": [325, 4, 397, 76], "X": [469.4, 555.6, 928.5, 911.8, 856.9, 290.1, 207.39999999999998, 58.400000000000006, 40.0], "Y": [337.0, 233.10000000000002, 201.3, 231.3, 118.19999999999999, 279.3, 226.3, 318.6, 366.0], "T": [205, 148, 283, 235, 245, 169, 130, 124], "target_object": "TBD", "max_fixations": 13, "subject_name": "JCG", "initial_fixation_row": 463, "initial_fixation_column": 383, "response_x": 40.0, "response_y": 366.0, "response_size": 31, "response_click": 1.48319257993717, "response_circle": 2.38353420014028}, "grayscale_85_oliva.jpg": {"subject": "31", "dataset": "Interiors Dataset", "image_height": 768, "image_width": 1024, "screen_height": 960, "screen_width": 1280, "receptive_height": 32, "receptive_width": 32, "target_found": true, "target_bbox": [256, 860, 328, 932], "X": [571.5, 836.1, 825.8, 942.8, 942.0, 897.0], "Y": [388.4, 401.79999999999995, 195.0, 191.89999999999998, 251.8, 294.0], "T": [936, 140, 211, 147, 197], "target_object": "bowl", "max_fixations": 13, "subject_name": "JCG", "initial_fixation_row": 650, "initial_fixation_column": 913, "response_x": 897.0, "response_y": 294.0, "response_size": 19, "response_click": 0.900250130507629, "response_circle": 1.50034865783527}, "grayscale_15_housebeautiful.jpg": {"subject": "31", "dataset": "Interiors Dataset", "image_height": 768, "image_width": 1024, "screen_height": 960, "screen_width": 1280, "receptive_height": 32, "receptive_width": 32, "target_found": true, "target_bbox": [587, 752, 659, 824], "X": [647.3, 736.5, 289.4, 278.3, 820.8, 786.0], "Y": [363.7, 530.0, 522.2, 495.6, 600.5, 603.0], "T": [175, 247, 219, 102, 1720], "target_object": "TBD", "max_fixations": 13, "subject_name": "JCG", "initial_fixation_row": 582, "initial_fixation_column": 432, "response_x": 786.0, "response_y": 603.0, "response_size": 21, "response_click": 1.73388901591534, "response_circle": 2.50044366635848}, "grayscale_14_other.jpg": {"subject": "31", "dataset": "Interiors Dataset", "image_height": 768, "image_width": 1024, "screen_height": 960, "screen_width": 1280, "receptive_height": 32, "receptive_width": 32, "target_found": false, "target_bbox": [438, 56, 510, 128], "X": [684.0, 487.5, 321.1, 656.6, 175.0], "Y": [512.0, 528.6, 553.9, 467.8, 488.0], "T": [249, 162, 286, 444], "target_object": "TBD", "max_fixations": 5, "subject_name": "JCG", "initial_fixation_row": 118, "initial_fixation_column": 134, "response_x": 175.0, "response_y": 488.0, "response_size": 139, "response_click": 2.10018297942588, "response_circle": 4.70010527182603}, "grayscale_6_opensource.jpg": {"subject": "31", "dataset": "Interiors Dataset", "image_height": 768, "image_width": 1024, "screen_height": 960, "screen_width": 1280, "receptive_height": 32, "receptive_width": 32, "target_found": false, "target_bbox": [172, 365, 244, 437], "X": [550.9, 352.4, 847.6, 991.8, 887.7, 552.75, 507.3, 521.1, 396.0], "Y": [387.8, 342.5, 393.6, 422.4, 649.2, 357.3, 356.0, 240.7, 201.0], "T": [649, 180, 289, 122, 218, 206, 205, 122, 503], "target_object": "TBD", "max_fixations": 9, "subject_name": "JCG", "initial_fixation_row": 468, "initial_fixation_column": 647, "response_x": 396.0, "response_y": 201.0, "response_size": 21, "response_click": 1.28346323699225, "response_circle": 1.95021259627538}, "grayscale_35_housebeautiful.jpg": {"subject": "31", "dataset": "Interiors Dataset", "image_height": 768, "image_width": 1024, "screen_height": 960, "screen_width": 1280, "receptive_height": 32, "receptive_width": 32, "target_found": true, "target_bbox": [368, 192, 440, 264], "X": [571.5, 361.2, 319.9, 216.60000000000002, 239.0], "Y": [195.5, 464.5, 379.4, 378.7, 387.0], "T": [359, 144, 143, 129], "target_object": "TBD", "max_fixations": 13, "subject_name": "JCG", "initial_fixation_row": 217, "initial_fixation_column": 534, "response_x": 239.0, "response_y": 387.0, "response_size": 19, "response_click": 1.58350604947191, "response_circle": 2.21697544440394}, "grayscale_83_oliva.jpg": {"subject": "31", "dataset": "Interiors Dataset", "image_height": 768, "image_width": 1024, "screen_height": 960, "screen_width": 1280, "receptive_height": 32, "receptive_width": 32, "target_found": true, "target_bbox": [561, 951, 633, 1023], "X": [509.1, 332.9, 515.8, 930.3, 977.9000000000001, 975.0], "Y": [379.0, 418.4, 659.5, 386.9, 583.7, 586.0], "T": [162, 204, 300, 205, 209], "target_object": "TBD", "max_fixations": 13, "subject_name": "JCG", "initial_fixation_row": 405, "initial_fixation_column": 685, "response_x": 975.0, "response_y": 586.0, "response_size": 23, "response_click": 1.08318085048813, "response_circle": 1.68335767195094}, "grayscale_3_kitchen.jpg": {"subject": "31", "dataset": "Interiors Dataset", "image_height": 768, "image_width": 1024, "screen_height": 960, "screen_width": 1280, "receptive_height": 32, "receptive_width": 32, "target_found": false, "target_bbox": [244, 53, 316, 125], "X": [520.0, 267.5, 131.7, 108.9, 93.0], "Y": [319.3, 278.1, 194.3, 201.39999999999998, 256.0], "T": [445, 118, 202, 566], "target_object": "TBD", "max_fixations": 13, "subject_name": "JCG", "initial_fixation_row": 531, "initial_fixation_column": 344, "response_x": 93.0, "response_y": 256.0, "response_size": 23, "response_click": 1.18361249420559, "response_circle": 2.05027329613222}, "grayscale_81_oliva.jpg": {"subject": "31", "dataset": "Interiors Dataset", "image_height": 768, "image_width": 1024, "screen_height": 960, "screen_width": 1280, "receptive_height": 32, "receptive_width": 32, "target_found": true, "target_bbox": [470, 927, 542, 999], "X": [452.6, 114.4, 895.4, 1004.0, 1008.0, 967.4000000000001, 945.0], "Y": [335.4, 369.5, 414.1, 334.0, 315.5, 547.6, 504.0], "T": [215, 116, 225, 319, 160, 89, 754], "target_object": "TBD", "max_fixations": 13, "subject_name": "JCG", "initial_fixation_row": 305, "initial_fixation_column": 667, "response_x": 945.0, "response_y": 504.0, "response_size": 33, "response_click": 1.38358375703683, "response_circle": 2.28357408026932}, "grayscale_27_housebeautiful.jpg": {"subject": "31", "dataset": "Interiors Dataset", "image_height": 768, "image_width": 1024, "screen_height": 960, "screen_width": 1280, "receptive_height": 32, "receptive_width": 32, "target_found": true, "target_bbox": [470, 98, 542, 170], "X": [786.9, 741.4, 328.6, 201.0, 125.69999999999999, 124.0], "Y": [483.5, 568.2, 504.79999999999995, 513.6, 550.8, 516.0], "T": [303, 215, 157, 144, 241, 306], "target_object": "bowl", "max_fixations": 13, "subject_name": "JCG", "initial_fixation_row": 151, "initial_fixation_column": 177, "response_x": 124.0, "response_y": 516.0, "response_size": 33, "response_click": 1.06682882632595, "response_circle": 2.13351220742334}, "grayscale_42_oliva.jpg": {"subject": "31", "dataset": "Interiors Dataset", "image_height": 768, "image_width": 1024, "screen_height": 960, "screen_width": 1280, "receptive_height": 32, "receptive_width": 32, "target_found": false, "target_bbox": [105, 228, 177, 300], "X": [490.29999999999995, 325.4, 316.5, 293.2, 268.0], "Y": [212.60000000000002, 120.80000000000001, 13.300000000000011, 83.80000000000001, 146.0], "T": [189, 80, 120, 1085], "target_object": "TBD", "max_fixations": 9, "subject_name": "JCG", "initial_fixation_row": 354, "initial_fixation_column": 552, "response_x": 268.0, "response_y": 146.0, "response_size": 17, "response_click": 0.733566749375314, "response_circle": 1.40055216377368}, "grayscale_1_oliva.jpg": {"subject": "31", "dataset": "Interiors Dataset", "image_height": 768, "image_width": 1024, "screen_height": 960, "screen_width": 1280, "receptive_height": 32, "receptive_width": 32, "target_found": false, "target_bbox": [605, 106, 677, 178], "X": [726.5, 506.6, 830.2, 613.7, 538.5, 254.3, 282.5, 999.8, 846.2, 1023.0, 608.6, 171.0], "Y": [556.4, 472.3, 402.8, 494.5, 339.5, 624.3, 674.0, 357.1, 360.6, 519.3, 328.2, 607.0], "T": [177, 184, 174, 149, 106, 244, 747, 268, 178, 132, 345], "target_object": "cup", "max_fixations": 13, "subject_name": "JCG", "initial_fixation_row": 718, "initial_fixation_column": 492, "response_x": 171.0, "response_y": 607.0, "response_size": 25, "response_click": 2.10021552862599, "response_circle": 3.03351865865989}, "grayscale_77_oliva.jpg": {"subject": "31", "dataset": "Interiors Dataset", "image_height": 768, "image_width": 1024, "screen_height": 960, "screen_width": 1280, "receptive_height": 32, "receptive_width": 32, "target_found": false, "target_bbox": [91, 28, 163, 100], "X": [458.29999999999995, 403.3, 524.8, 847.1, 940.0999999999999, 712.4, 547.7, 121.69999999999999, 99.1, 85.0], "Y": [318.9, 198.89999999999998, 318.2, 254.2, 384.20000000000005, 457.20000000000005, 430.9, 33.400000000000006, 68.69999999999999, 131.0], "T": [253, 69, 139, 154, 158, 136, 74, 237, 180], "target_object": "TBD", "max_fixations": 9, "subject_name": "JCG", "initial_fixation_row": 340, "initial_fixation_column": 352, "response_x": 85.0, "response_y": 131.0, "response_size": 15, "response_click": 1.30034777818946, "response_circle": 1.93369254772551}, "grayscale_44_oliva.jpg": {"subject": "31", "dataset": "Interiors Dataset", "image_height": 768, "image_width": 1024, "screen_height": 960, "screen_width": 1280, "receptive_height": 32, "receptive_width": 32, "target_found": true, "target_bbox": [316, 298, 388, 370], "X": [515.5, 405.4, 747.6, 501.9, 286.5, 330.0], "Y": [349.7, 391.79999999999995, 387.4, 361.7, 364.0, 340.0], "T": [274, 60, 196, 154, 147, 228], "target_object": "bowl", "max_fixations": 13, "subject_name": "JCG", "initial_fixation_row": 213, "initial_fixation_column": 664, "response_x": 330.0, "response_y": 340.0, "response_size": 19, "response_click": 1.85001583473058, "response_circle": 2.55014309927355}, "grayscale_62_oliva.jpg": {"subject": "31", "dataset": "Interiors Dataset", "image_height": 768, "image_width": 1024, "screen_height": 960, "screen_width": 1280, "receptive_height": 32, "receptive_width": 32, "target_found": false, "target_bbox": [360, 265, 432, 337], "X": [613.3, 607.6, 419.1, 294.4, 269.4, 412.65, 289.5, 268.4, 296.1, 386.9, 405.70000000000005, 313.0], "Y": [485.2, 517.1, 569.7, 608.0, 620.2, 557.4000000000001, 584.4, 615.0, 579.7, 563.0, 555.0, 390.0], "T": [674, 123, 275, 216, 219, 779, 1126, 158, 229, 20, 205, 216, 388], "target_object": "TBD", "max_fixations": 13, "subject_name": "JCG", "initial_fixation_row": 417, "initial_fixation_column": 658, "response_x": 313.0, "response_y": 390.0, "response_size": 15, "response_click": 2.11694905313198, "response_circle": 2.75026391260326}, "grayscale_64_oliva.jpg": {"subject": "31", "dataset": "Interiors Dataset", "image_height": 768, "image_width": 1024, "screen_height": 960, "screen_width": 1280, "receptive_height": 32, "receptive_width": 32, "target_found": true, "target_bbox": [312, 214, 384, 286], "X": [568.3, 656.5, 524.6, 160.7, 246.89999999999998, 261.0], "Y": [418.9, 402.1, 386.6, 365.2, 360.5, 330.0], "T": [377, 154, 121, 249, 356], "target_object": "TBD", "max_fixations": 13, "subject_name": "JCG", "initial_fixation_row": 394, "initial_fixation_column": 605, "response_x": 261.0, "response_y": 330.0, "response_size": 17, "response_click": 1.31687515758676, "response_circle": 1.95042900455883}, "grayscale_10_kitchen.jpg": {"subject": "31", "dataset": "Interiors Dataset", "image_height": 768, "image_width": 1024, "screen_height": 960, "screen_width": 1280, "receptive_height": 32, "receptive_width": 32, "target_found": false, "target_bbox": [497, 851, 569, 923], "X": [577.8, 342.6, 617.8, 756.0, 856.0], "Y": [472.2, 387.8, 416.5, 570.4, 500.0], "T": [216, 346, 186, 86], "target_object": "cup", "max_fixations": 5, "subject_name": "JCG", "initial_fixation_row": 249, "initial_fixation_column": 669, "response_x": 856.0, "response_y": 500.0, "response_size": 51, "response_click": 1.03356117784278, "response_circle": 2.03359284735052}, "grayscale_43_oliva.jpg": {"subject": "31", "dataset": "Interiors Dataset", "image_height": 768, "image_width": 1024, "screen_height": 960, "screen_width": 1280, "receptive_height": 32, "receptive_width": 32, "target_found": false, "target_bbox": [111, 750, 183, 822], "X": [617.1, 763.4, 908.0, 810.0, 659.3, 289.6, 314.8, 269.2, 902.4, 929.5, 898.65, 795.0], "Y": [473.1, 538.7, 402.1, 374.4, 381.2, 420.6, 767.0, 767.0, 337.5, 280.5, 286.4, 135.0], "T": [327, 119, 183, 195, 130, 556, 168, 101, 200, 218, 659, 352], "target_object": "potted plant", "max_fixations": 13, "subject_name": "JCG", "initial_fixation_row": 311, "initial_fixation_column": 468, "response_x": 795.0, "response_y": 135.0, "response_size": 35, "response_click": 1.06677135202335, "response_circle": 2.0335227639298}, "grayscale_86_oliva.jpg": {"subject": "31", "dataset": "Interiors Dataset", "image_height": 768, "image_width": 1024, "screen_height": 960, "screen_width": 1280, "receptive_height": 32, "receptive_width": 32, "target_found": true, "target_bbox": [344, 826, 416, 898], "X": [689.9, 478.20000000000005, 895.6, 870.0], "Y": [424.70000000000005, 299.4, 420.1, 364.0], "T": [319, 195, 273, 2408], "target_object": "potted plant", "max_fixations": 9, "subject_name": "JCG", "initial_fixation_row": 697, "initial_fixation_column": 696, "response_x": 870.0, "response_y": 364.0, "response_size": 31, "response_click": 1.31695697054965, "response_circle": 2.91697691060835}, "grayscale_2_oliva.jpg": {"subject": "31", "dataset": "Interiors Dataset", "image_height": 768, "image_width": 1024, "screen_height": 960, "screen_width": 1280, "receptive_height": 32, "receptive_width": 32, "target_found": true, "target_bbox": [306, 951, 378, 1023], "X": [583.9, 336.5, 879.9, 995.9000000000001, 990.0], "Y": [366.2, 326.6, 321.2, 330.0, 327.0], "T": [887, 209, 143, 159], "target_object": "TBD", "max_fixations": 13, "subject_name": "JCG", "initial_fixation_row": 7, "initial_fixation_column": 862, "response_x": 990.0, "response_y": 327.0, "response_size": 21, "response_click": 1.18356381694321, "response_circle": 2.15024514542893}, "grayscale_38_housebeautiful.jpg": {"subject": "31", "dataset": "Interiors Dataset", "image_height": 768, "image_width": 1024, "screen_height": 960, "screen_width": 1280, "receptive_height": 32, "receptive_width": 32, "target_found": true, "target_bbox": [402, 909, 474, 981], "X": [693.0, 989.2, 948.0], "Y": [374.4, 446.79999999999995, 428.0], "T": [258, 174], "target_object": "TBD", "max_fixations": 9, "subject_name": "JCG", "initial_fixation_row": 372, "initial_fixation_column": 593, "response_x": 948.0, "response_y": 428.0, "response_size": 23, "response_click": 1.21687457110966, "response_circle": 1.88363595306873}, "grayscale_23_oliva.jpg": {"subject": "31", "dataset": "Interiors Dataset", "image_height": 768, "image_width": 1024, "screen_height": 960, "screen_width": 1280, "receptive_height": 32, "receptive_width": 32, "target_found": false, "target_bbox": [482, 793, 554, 865], "X": [616.7, 654.7, 880.0, 969.2, 952.2, 980.6, 819.0], "Y": [543.9, 579.7, 690.7, 681.0, 675.5, 663.9, 505.0], "T": [1834, 144, 211, 232, 510, 41], "target_object": "knife", "max_fixations": 5, "subject_name": "JCG", "initial_fixation_row": 530, "initial_fixation_column": 471, "response_x": 819.0, "response_y": 505.0, "response_size": 21, "response_click": 1.63353625277523, "response_circle": 2.40021288947901}, "grayscale_22_housebeautiful.jpg": {"subject": "31", "dataset": "Interiors Dataset", "image_height": 768, "image_width": 1024, "screen_height": 960, "screen_width": 1280, "receptive_height": 32, "receptive_width": 32, "target_found": false, "target_bbox": [267, 136, 339, 208], "X": [903.9, 1023.0, 276.2, 257.0, 253.79999999999998, 201.4, 244.675, 178.0], "Y": [567.2, 565.3, 516.9, 422.6, 441.775, 440.7, 439.025, 304.0], "T": [277, 130, 255, 169, 855, 276, 25, 145, 700, 249, 359], "target_object": "TBD", "max_fixations": 13, "subject_name": "JCG", "initial_fixation_row": 53, "initial_fixation_column": 429, "response_x": 178.0, "response_y": 304.0, "response_size": 27, "response_click": 1.38353918516077, "response_circle": 2.35025423578918}, "grayscale_88_oliva.jpg": {"subject": "31", "dataset": "Interiors Dataset", "image_height": 768, "image_width": 1024, "screen_height": 960, "screen_width": 1280, "receptive_height": 32, "receptive_width": 32, "target_found": false, "target_bbox": [276, 0, 348, 72], "X": [643.5, 964.3, 991.8, 636.2, 618.1, 415.0], "Y": [598.1, 564.5, 396.9, 383.4, 449.1, 250.0], "T": [274, 167, 263, 272, 690], "target_object": "TBD", "max_fixations": 5, "subject_name": "JCG", "initial_fixation_row": 619, "initial_fixation_column": 220, "response_x": 415.0, "response_y": 250.0, "response_size": 299, "response_click": 1.73363624635385, "response_circle": 7.1336617579218}, "grayscale_9_other.jpg": {"subject": "31", "dataset": "Interiors Dataset", "image_height": 768, "image_width": 1024, "screen_height": 960, "screen_width": 1280, "receptive_height": 32, "receptive_width": 32, "target_found": true, "target_bbox": [292, 807, 364, 879], "X": [446.79999999999995, 805.5, 710.0, 809.0, 828.0], "Y": [416.5, 419.0, 436.70000000000005, 312.2, 327.0], "T": [273, 244, 160, 151], "target_object": "TBD", "max_fixations": 13, "subject_name": "JCG", "initial_fixation_row": 261, "initial_fixation_column": 491, "response_x": 828.0, "response_y": 327.0, "response_size": 21, "response_click": 1.36690712033305, "response_circle": 1.96703321189852}, "grayscale_29_housebeautiful.jpg": {"subject": "31", "dataset": "Interiors Dataset", "image_height": 768, "image_width": 1024, "screen_height": 960, "screen_width": 1280, "receptive_height": 32, "receptive_width": 32, "target_found": true, "target_bbox": [132, 207, 204, 279], "X": [572.0, 307.4, 959.3, 965.4000000000001, 950.2, 208.8, 247.0], "Y": [394.9, 363.3, 350.4, 215.5, 432.20000000000005, 196.89999999999998, 160.0], "T": [309, 131, 201, 148, 146, 214], "target_object": "TBD", "max_fixations": 9, "subject_name": "JCG", "initial_fixation_row": 396, "initial_fixation_column": 519, "response_x": 247.0, "response_y": 160.0, "response_size": 23, "response_click": 1.53369899885729, "response_circle": 2.26708335528383}, "grayscale_65_oliva.jpg": {"subject": "31", "dataset": "Interiors Dataset", "image_height": 768, "image_width": 1024, "screen_height": 960, "screen_width": 1280, "receptive_height": 32, "receptive_width": 32, "target_found": true, "target_bbox": [233, 898, 305, 970], "X": [751.4, 908.8, 921.0], "Y": [300.0, 249.7, 298.0], "T": [217, 153], "target_object": "bowl", "max_fixations": 5, "subject_name": "JCG", "initial_fixation_row": 429, "initial_fixation_column": 614, "response_x": 921.0, "response_y": 298.0, "response_size": 33, "response_click": 1.18349519971525, "response_circle": 2.38361366715981}, "grayscale_74_oliva.jpg": {"subject": "31", "dataset": "Interiors Dataset", "image_height": 768, "image_width": 1024, "screen_height": 960, "screen_width": 1280, "receptive_height": 32, "receptive_width": 32, "target_found": true, "target_bbox": [190, 492, 262, 564], "X": [848.1, 825.9, 1023.0, 1020.8, 1023.0, 516.0, 992.4000000000001, 1008.7, 554.3, 515.0], "Y": [435.20000000000005, 335.5, 261.2, 381.6, 232.89999999999998, 296.6, 437.5, 406.0, 209.3, 224.0], "T": [449, 158, 146, 216, 348, 150, 169, 130, 1250], "target_object": "TBD", "max_fixations": 13, "subject_name": "JCG", "initial_fixation_row": 487, "initial_fixation_column": 773, "response_x": 515.0, "response_y": 224.0, "response_size": 17, "response_click": 1.25020203978056, "response_circle": 1.75042753841262}, "grayscale_23_housebeautiful.jpg": {"subject": "31", "dataset": "Interiors Dataset", "image_height": 768, "image_width": 1024, "screen_height": 960, "screen_width": 1280, "receptive_height": 32, "receptive_width": 32, "target_found": true, "target_bbox": [647, 561, 719, 633], "X": [659.1, 757.3, 543.2, 505.20000000000005, 629.4, 593.0], "Y": [418.79999999999995, 519.9, 535.0, 666.0, 635.9, 663.0], "T": [617, 71, 214, 143, 225], "target_object": "TBD", "max_fixations": 9, "subject_name": "JCG", "initial_fixation_row": 500, "initial_fixation_column": 904, "response_x": 593.0, "response_y": 663.0, "response_size": 21, "response_click": 2.20018121995963, "response_circle": 2.93355531309498}, "grayscale_28_housebeautiful.jpg": {"subject": "31", "dataset": "Interiors Dataset", "image_height": 768, "image_width": 1024, "screen_height": 960, "screen_width": 1280, "receptive_height": 32, "receptive_width": 32, "target_found": false, "target_bbox": [523, 94, 595, 166], "X": [503.8, 528.6, 199.0], "Y": [457.9, 609.7, 511.0], "T": [240, 583], "target_object": "potted plant", "max_fixations": 5, "subject_name": "JCG", "initial_fixation_row": 299, "initial_fixation_column": 376, "response_x": 199.0, "response_y": 511.0, "response_size": 107, "response_click": 1.91692002274795, "response_circle": 4.71692676719977}, "grayscale_31_oliva.jpg": {"subject": "31", "dataset": "Interiors Dataset", "image_height": 768, "image_width": 1024, "screen_height": 960, "screen_width": 1280, "receptive_height": 32, "receptive_width": 32, "target_found": false, "target_bbox": [227, 614, 299, 686], "X": [905.7, 759.7, 641.0], "Y": [502.9, 398.2, 268.0], "T": [242, 950], "target_object": "TBD", "max_fixations": 3, "subject_name": "JCG", "initial_fixation_row": 174, "initial_fixation_column": 303, "response_x": 641.0, "response_y": 268.0, "response_size": 21, "response_click": 1.01723290578229, "response_circle": 1.65056653239299}, "grayscale_2_opensource.jpg": {"subject": "31", "dataset": "Interiors Dataset", "image_height": 768, "image_width": 1024, "screen_height": 960, "screen_width": 1280, "receptive_height": 32, "receptive_width": 32, "target_found": true, "target_bbox": [266, 881, 338, 953], "X": [843.4, 873.6, 899.0], "Y": [393.5, 265.8, 293.0], "T": [298, 92, 143], "target_object": "TBD", "max_fixations": 9, "subject_name": "JCG", "initial_fixation_row": 561, "initial_fixation_column": 670, "response_x": 899.0, "response_y": 293.0, "response_size": 21, "response_click": 1.38357818557415, "response_circle": 1.98361249419395}, "grayscale_16_opensource.jpg": {"subject": "31", "dataset": "Interiors Dataset", "image_height": 768, "image_width": 1024, "screen_height": 960, "screen_width": 1280, "receptive_height": 32, "receptive_width": 32, "target_found": false, "target_bbox": [364, 929, 436, 1001], "X": [690.2, 992.1, 1023.0, 1023.0, 1023.0, 1023.0, 981.9, 468.5, 942.0], "Y": [459.7, 558.0, 546.646875, 175.3, 624.3, 561.0, 560.2, 472.4, 410.0], "T": [370, 254, 542, 204, 41, 134, 151, 163, 226, 108, 192, 181, 397], "target_object": "potted plant", "max_fixations": 13, "subject_name": "JCG", "initial_fixation_row": 42, "initial_fixation_column": 972, "response_x": 942.0, "response_y": 410.0, "response_size": 23, "response_click": 1.43342423660215, "response_circle": 2.06697691063164}, "grayscale_37_oliva.jpg": {"subject": "31", "dataset": "Interiors Dataset", "image_height": 768, "image_width": 1024, "screen_height": 960, "screen_width": 1280, "receptive_height": 32, "receptive_width": 32, "target_found": false, "target_bbox": [369, 201, 441, 273], "X": [752.2, 952.9, 278.0], "Y": [551.3, 545.2, 372.0], "T": [258, 532], "target_object": "TBD", "max_fixations": 3, "subject_name": "JCG", "initial_fixation_row": 62, "initial_fixation_column": 341, "response_x": 278.0, "response_y": 372.0, "response_size": 51, "response_click": 1.83352159103379, "response_circle": 3.00022110011196}, "grayscale_94_oliva.jpg": {"subject": "31", "dataset": "Interiors Dataset", "image_height": 768, "image_width": 1024, "screen_height": 960, "screen_width": 1280, "receptive_height": 32, "receptive_width": 32, "target_found": true, "target_bbox": [215, 869, 287, 941], "X": [729.0, 523.7, 818.6, 924.6, 890.0], "Y": [357.8, 322.7, 194.0, 222.3, 237.0], "T": [527, 79, 131, 202], "target_object": "potted plant", "max_fixations": 9, "subject_name": "JCG", "initial_fixation_row": 592, "initial_fixation_column": 1013, "response_x": 890.0, "response_y": 237.0, "response_size": 27, "response_click": 1.3002888376941, "response_circle": 2.16692324838368}, "grayscale_71_oliva.jpg": {"subject": "31", "dataset": "Interiors Dataset", "image_height": 768, "image_width": 1024, "screen_height": 960, "screen_width": 1280, "receptive_height": 32, "receptive_width": 32, "target_found": false, "target_bbox": [357, 346, 429, 418], "X": [738.9, 552.2, 968.5, 270.4, 520.0, 486.35, 397.0], "Y": [604.1, 617.5, 686.1, 615.9, 575.5, 554.35, 391.0], "T": [269, 141, 121, 185, 132, 326, 345], "target_object": "TBD", "max_fixations": 9, "subject_name": "JCG", "initial_fixation_row": 512, "initial_fixation_column": 719, "response_x": 397.0, "response_y": 391.0, "response_size": 23, "response_click": 1.53357671934646, "response_circle": 2.23362099804217}, "grayscale_39_housebeautiful.jpg": {"subject": "31", "dataset": "Interiors Dataset", "image_height": 768, "image_width": 1024, "screen_height": 960, "screen_width": 1280, "receptive_height": 32, "receptive_width": 32, "target_found": true, "target_bbox": [566, 579, 638, 651], "X": [564.8, 318.4, 643.9, 602.0], "Y": [433.9, 544.8, 592.8, 592.0], "T": [494, 127, 201], "target_object": "TBD", "max_fixations": 9, "subject_name": "JCG", "initial_fixation_row": 405, "initial_fixation_column": 914, "response_x": 602.0, "response_y": 592.0, "response_size": 35, "response_click": 1.50019060348859, "response_circle": 2.53363008837914}, "grayscale_20_opensource.jpg": {"subject": "31", "dataset": "Interiors Dataset", "image_height": 768, "image_width": 1024, "screen_height": 960, "screen_width": 1280, "receptive_height": 32, "receptive_width": 32, "target_found": true, "target_bbox": [166, 370, 238, 442], "X": [546.5, 601.8, 597.1, 684.8, 446.4, 414.0], "Y": [408.5, 296.6, 162.5, 197.89999999999998, 194.8, 199.0], "T": [212, 169, 237, 122, 300], "target_object": "cup", "max_fixations": 9, "subject_name": "JCG", "initial_fixation_row": 313, "initial_fixation_column": 66, "response_x": 414.0, "response_y": 199.0, "response_size": 21, "response_click": 1.1168575634365, "response_circle": 1.81688102235785}, "grayscale_4_kitchen.jpg": {"subject": "31", "dataset": "Interiors Dataset", "image_height": 768, "image_width": 1024, "screen_height": 960, "screen_width": 1280, "receptive_height": 32, "receptive_width": 32, "target_found": false, "target_bbox": [13, 408, 85, 480], "X": [841.7, 617.6, 424.4, 345.9, 838.4, 784.2, 908.2, 886.5, 836.1, 633.2, 932.6, 742.1, 458.0], "Y": [460.0, 462.7, 461.9, 456.1, 461.9, 458.8, 463.1, 683.8, 611.7, 583.0, 501.2, 177.2, 76.0], "T": [293, 253, 263, 181, 248, 54, 117, 191, 304, 108, 120, 511], "target_object": "TBD", "max_fixations": 13, "subject_name": "JCG", "initial_fixation_row": 318, "initial_fixation_column": 681, "response_x": 458.0, "response_y": 76.0, "response_size": 23, "response_click": 1.80029939417727, "response_circle": 2.36712176923174}, "grayscale_10_housebeautiful.jpg": {"subject": "31", "dataset": "Interiors Dataset", "image_height": 768, "image_width": 1024, "screen_height": 960, "screen_width": 1280, "receptive_height": 32, "receptive_width": 32, "target_found": false, "target_bbox": [520, 30, 592, 102], "X": [638.2, 644.5, 736.9, 724.0], "Y": [447.7, 488.0, 665.5, 491.0], "T": [490, 138, 706], "target_object": "potted plant", "max_fixations": 3, "subject_name": "JCG", "initial_fixation_row": 373, "initial_fixation_column": 374, "response_x": 724.0, "response_y": 491.0, "response_size": 197, "response_click": 2.43353156099329, "response_circle": 5.86701033951249}, "grayscale_40_oliva.jpg": {"subject": "31", "dataset": "Interiors Dataset", "image_height": 768, "image_width": 1024, "screen_height": 960, "screen_width": 1280, "receptive_height": 32, "receptive_width": 32, "target_found": false, "target_bbox": [393, 16, 465, 88], "X": [624.8, 435.9, 513.3, 137.0], "Y": [497.5, 548.4, 599.7, 447.0], "T": [485, 228, 524], "target_object": "TBD", "max_fixations": 3, "subject_name": "JCG", "initial_fixation_row": 74, "initial_fixation_column": 7, "response_x": 137.0, "response_y": 447.0, "response_size": 61, "response_click": 1.31674173509236, "response_circle": 2.78356498992071}, "grayscale_8_other.jpg": {"subject": "31", "dataset": "Interiors Dataset", "image_height": 768, "image_width": 1024, "screen_height": 960, "screen_width": 1280, "receptive_height": 32, "receptive_width": 32, "target_found": false, "target_bbox": [11, 373, 83, 445], "X": [887.7, 1023.0, 1023.0, 916.6, 481.5, 357.2, 322.2, 409.0], "Y": [326.9, 223.3, 353.6, 440.8, 451.8, 392.6, 385.0, 237.0], "T": [361, 199, 235, 215, 226, 187, 277], "target_object": "TBD", "max_fixations": 9, "subject_name": "JCG", "initial_fixation_row": 399, "initial_fixation_column": 473, "response_x": 409.0, "response_y": 237.0, "response_size": 295, "response_click": 0.783663810580038, "response_circle": 6.08362451690482}, "grayscale_15_oliva.jpg": {"subject": "31", "dataset": "Interiors Dataset", "image_height": 768, "image_width": 1024, "screen_height": 960, "screen_width": 1280, "receptive_height": 32, "receptive_width": 32, "target_found": true, "target_bbox": [416, 661, 488, 733], "X": [624.45, 646.9, 612.4, 765.2, 873.2, 802.1, 683.9, 696.0], "Y": [463.45, 526.2, 362.3, 434.9, 526.5, 476.70000000000005, 444.0, 442.0], "T": [305, 181, 172, 251, 130, 263, 125, 188], "target_object": "fork", "max_fixations": 13, "subject_name": "JCG", "initial_fixation_row": 608, "initial_fixation_column": 375, "response_x": 696.0, "response_y": 442.0, "response_size": 69, "response_click": 1.53362539660884, "response_circle": 3.0336796452757}, "grayscale_14_kitchen.jpg": {"subject": "31", "dataset": "Interiors Dataset", "image_height": 768, "image_width": 1024, "screen_height": 960, "screen_width": 1280, "receptive_height": 32, "receptive_width": 32, "target_found": true, "target_bbox": [344, 1, 416, 73], "X": [611.1, 564.0, 783.0, 866.1, 403.1, 174.7, 72.4, 37.0], "Y": [341.4, 319.8, 333.9, 328.1, 346.7, 344.9, 351.2, 388.0], "T": [359, 144, 212, 157, 147, 127, 1135], "target_object": "potted plant", "max_fixations": 13, "subject_name": "JCG", "initial_fixation_row": 661, "initial_fixation_column": 259, "response_x": 37.0, "response_y": 388.0, "response_size": 21, "response_click": 0.866919436259195, "response_circle": 1.50033018394606}, "grayscale_59_oliva.jpg": {"subject": "31", "dataset": "Interiors Dataset", "image_height": 768, "image_width": 1024, "screen_height": 960, "screen_width": 1280, "receptive_height": 32, "receptive_width": 32, "target_found": true, "target_bbox": [472, 800, 544, 872], "X": [604.3, 660.5, 862.8, 832.0], "Y": [373.1, 414.6, 509.9, 506.0], "T": [641, 157, 315], "target_object": "TBD", "max_fixations": 9, "subject_name": "JCG", "initial_fixation_row": 603, "initial_fixation_column": 491, "response_x": 832.0, "response_y": 506.0, "response_size": 25, "response_click": 1.48361894540722, "response_circle": 2.18356088461587}, "grayscale_92_oliva.jpg": {"subject": "31", "dataset": "Interiors Dataset", "image_height": 768, "image_width": 1024, "screen_height": 960, "screen_width": 1280, "receptive_height": 32, "receptive_width": 32, "target_found": false, "target_bbox": [337, 227, 409, 299], "X": [661.3, 620.3, 377.3, 509.0], "Y": [476.8, 497.9, 654.2, 370.0], "T": [258, 190, 301], "target_object": "TBD", "max_fixations": 3, "subject_name": "JCG", "initial_fixation_row": 27, "initial_fixation_column": 354, "response_x": 509.0, "response_y": 370.0, "response_size": 39, "response_click": 1.31675375782652, "response_circle": 2.083673194109}, "grayscale_55_oliva.jpg": {"subject": "31", "dataset": "Interiors Dataset", "image_height": 768, "image_width": 1024, "screen_height": 960, "screen_width": 1280, "receptive_height": 32, "receptive_width": 32, "target_found": false, "target_bbox": [144, 205, 216, 277], "X": [669.1, 605.2, 587.1, 829.0, 1023.0, 975.4, 346.1, 351.7, 235.0], "Y": [476.8, 476.9, 489.8, 482.2, 494.7, 513.2, 497.2, 334.4, 186.0], "T": [298, 206, 40, 199, 189, 142, 316, 525], "target_object": "bottle", "max_fixations": 9, "subject_name": "JCG", "initial_fixation_row": 154, "initial_fixation_column": 598, "response_x": 235.0, "response_y": 186.0, "response_size": 23, "response_click": 1.60026361938799, "response_circle": 2.20032989076572}, "grayscale_73_oliva.jpg": {"subject": "31", "dataset": "Interiors Dataset", "image_height": 768, "image_width": 1024, "screen_height": 960, "screen_width": 1280, "receptive_height": 32, "receptive_width": 32, "target_found": false, "target_bbox": [577, 322, 649, 394], "X": [649.2, 503.3, 340.0, 673.5, 338.1, 362.1, 345.0], "Y": [474.1, 433.9, 504.8, 693.0, 685.7, 725.8, 566.0], "T": [1334, 136, 152, 214, 279, 434], "target_object": "TBD", "max_fixations": 5, "subject_name": "JCG", "initial_fixation_row": 267, "initial_fixation_column": 267, "response_x": 345.0, "response_y": 566.0, "response_size": 69, "response_click": 1.36695814348059, "response_circle": 2.80034337961115}, "grayscale_30_opensource.jpg": {"subject": "31", "dataset": "Interiors Dataset", "image_height": 768, "image_width": 1024, "screen_height": 960, "screen_width": 1280, "receptive_height": 32, "receptive_width": 32, "target_found": true, "target_bbox": [240, 800, 312, 872], "X": [711.3, 706.3, 746.7, 713.6, 565.5, 487.7, 422.2, 764.9, 764.2, 807.5, 842.4, 631.0], "Y": [420.2, 372.5, 292.7, 201.3, 344.2, 414.0, 409.4, 540.5, 309.4, 394.1, 324.5, 353.0], "T": [213, 215, 143, 148, 125, 230, 168, 205, 195, 124, 216, 284], "target_object": "potted plant", "max_fixations": 13, "subject_name": "JCG", "initial_fixation_row": 180, "initial_fixation_column": 491, "response_x": 631.0, "response_y": 353.0, "response_size": 93, "response_click": 1.46698189561721, "response_circle": 3.23366146464832}, "grayscale_3_other.jpg": {"subject": "31", "dataset": "Interiors Dataset", "image_height": 768, "image_width": 1024, "screen_height": 960, "screen_width": 1280, "receptive_height": 32, "receptive_width": 32, "target_found": false, "target_bbox": [404, 211, 476, 283], "X": [662.4, 739.4, 411.1, 334.8, 353.20000000000005, 330.425, 307.5, 338.6, 256.0], "Y": [495.2, 511.79999999999995, 566.6, 586.7, 582.3499999999999, 590.65, 587.0, 591.8499999999999, 438.0], "T": [241, 164, 169, 498, 210, 861, 228, 265, 315, 282, 272, 304], "target_object": "TBD", "max_fixations": 13, "subject_name": "JCG", "initial_fixation_row": 83, "initial_fixation_column": 279, "response_x": 256.0, "response_y": 438.0, "response_size": 17, "response_click": 2.43368873558939, "response_circle": 3.00028707820456}, "grayscale_1_housebeautiful.jpg": {"subject": "31", "dataset": "Interiors Dataset", "image_height": 768, "image_width": 1024, "screen_height": 960, "screen_width": 1280, "receptive_height": 32, "receptive_width": 32, "target_found": false, "target_bbox": [155, 130, 227, 202], "X": [704.4, 539.4, 787.8, 1023.0, 382.9, 422.7, 317.6, 282.6, 271.2, 137.0], "Y": [494.8, 559.7, 651.7, 630.2, 522.2, 383.6, 762.5, 767.0, 389.3, 181.0], "T": [361, 273, 253, 190, 235, 260, 149, 118, 452], "target_object": "clock", "max_fixations": 9, "subject_name": "JCG", "initial_fixation_row": 113, "initial_fixation_column": 515, "response_x": 137.0, "response_y": 181.0, "response_size": 27, "response_click": 0.966940256010275, "response_circle": 1.73369049502071}, "grayscale_14_oliva.jpg": {"subject": "31", "dataset": "Interiors Dataset", "image_height": 768, "image_width": 1024, "screen_height": 960, "screen_width": 1280, "receptive_height": 32, "receptive_width": 32, "target_found": true, "target_bbox": [287, 808, 359, 880], "X": [1008.7, 728.4, 857.5, 848.0], "Y": [658.1, 442.5, 332.8, 306.0], "T": [204, 238, 114], "target_object": "TBD", "max_fixations": 13, "subject_name": "JCG", "initial_fixation_row": 652, "initial_fixation_column": 986, "response_x": 848.0, "response_y": 306.0, "response_size": 23, "response_click": 1.06684348813724, "response_circle": 1.63357173441909}, "grayscale_1_kitchen.jpg": {"subject": "31", "dataset": "Interiors Dataset", "image_height": 768, "image_width": 1024, "screen_height": 960, "screen_width": 1280, "receptive_height": 32, "receptive_width": 32, "target_found": false, "target_bbox": [270, 855, 342, 927], "X": [578.2, 483.0, 913.4, 870.4, 947.4, 1023.0, 1023.0, 1023.0, 249.0], "Y": [507.9, 446.3, 586.5, 555.3, 426.6, 593.3, 569.1, 596.9, 464.0], "T": [328, 210, 304, 126, 109, 169, 266, 154, 283], "target_object": "bowl", "max_fixations": 9, "subject_name": "JCG", "initial_fixation_row": 620, "initial_fixation_column": 718, "response_x": 249.0, "response_y": 464.0, "response_size": 75, "response_click": 2.95020086679142, "response_circle": 4.38365999847883}, "grayscale_7_opensource.jpg": {"subject": "31", "dataset": "Interiors Dataset", "image_height": 768, "image_width": 1024, "screen_height": 960, "screen_width": 1280, "receptive_height": 32, "receptive_width": 32, "target_found": false, "target_bbox": [358, 82, 430, 154], "X": [670.6, 452.4, 443.6, 147.3, 117.0], "Y": [347.1, 410.5, 553.1, 341.2, 372.0], "T": [205, 195, 366, 274], "target_object": "TBD", "max_fixations": 9, "subject_name": "JCG", "initial_fixation_row": 54, "initial_fixation_column": 6, "response_x": 117.0, "response_y": 372.0, "response_size": 25, "response_click": 1.100243679306, "response_circle": 1.8002554087434}, "grayscale_5_housebeautiful.jpg": {"subject": "31", "dataset": "Interiors Dataset", "image_height": 768, "image_width": 1024, "screen_height": 960, "screen_width": 1280, "receptive_height": 32, "receptive_width": 32, "target_found": true, "target_bbox": [239, 433, 311, 505], "X": [550.9, 684.9, 492.20000000000005, 473.0], "Y": [319.4, 426.4, 300.6, 249.0], "T": [2075, 156, 234], "target_object": "bottle", "max_fixations": 5, "subject_name": "JCG", "initial_fixation_row": 147, "initial_fixation_column": 135, "response_x": 473.0, "response_y": 249.0, "response_size": 23, "response_click": 1.51684172864771, "response_circle": 2.15028825117042}}